Workbook
Name Slicer_Product_category: #N/A
Name Slicer_Store_ID: #N/A

Sheet Customer_Dim
A1: Customer_ID | B1: Name | C1: Name2 | D1: NAME 2 | E1: Age | F1: Gender | G1: City | H1: State | I1: Country | J1: Loyalty_Level | K1: Loyalty_Level3 | L1: Age Category
A2: CUST1000 | B2: sheena bonilla | C2: =PROPER(B2) -> Sheena Bonilla | D2: =TRIM(C2) -> Sheena Bonilla | E2: 55 | F2: Male | G2: Donaldton | H2: North Carolina | I2: USA | K2: =IF(ISBLANK(J2),"UNKNOWN",J2) -> UNKNOWN | L2: =IF(Customer_Dim[[#This Row],[Age]]<25,"Youth", IF(Customer_Dim[[#This Row],[Age]]<=40,"Adult", IF(Customer_Dim[[#This Row],[Age]]<=60,"Middle-Aged","Senior"))) -> Middle-Aged
A3: CUST1001 | B3: Eugene Nelson | C3: =PROPER(B3) -> Eugene Nelson | D3: =TRIM(C3) -> Eugene Nelson | E3: 26 | F3: Female | G3: Phillipsmouth | H3: North Dakota | I3: USA | J3: Platinum | K3: =IF(ISBLANK(J3),"UNKNOWN",J3) -> Platinum | L3: =IF(Customer_Dim[[#This Row],[Age]]<25,"Youth", IF(Customer_Dim[[#This Row],[Age]]<=40,"Adult", IF(Customer_Dim[[#This Row],[Age]]<=60,"Middle-Aged","Senior"))) -> Adult
A4: CUST1002 | B4: dr. Benjamin Price | C4: =PROPER(B4) -> Dr. Benjamin Price | D4: =TRIM(C4) -> Dr. Benjamin Price | E4: 29 | F4: Female | G4: Kylebury | H4: Alabama | I4: USA | J4: Platinum | K4: =IF(ISBLANK(J4),"UNKNOWN",J4) -> Platinum | L4: =IF(Customer_Dim[[#This Row],[Age]]<25,"Youth", IF(Customer_Dim[[#This Row],[Age]]<=40,"Adult", IF(Customer_Dim[[#This Row],[Age]]<=60,"Middle-Aged","Senior"))) -> Adult
A5: CUST1003 | B5: jeremy harris | C5: =PROPER(B5) -> Jeremy Harris | D5: =TRIM(C5) -> Jeremy Harris | E5: 59 | F5: Female | G5: Thomastown | H5: Ohio | I5: USA | J5: Bronze | K5: =IF(ISBLANK(J5),"UNKNOWN",J5) -> Bronze | L5: =IF(Customer_Dim[[#This Row],[Age]]<25,"Youth", IF(Customer_Dim[[#This Row],[Age]]<=40,"Adult", IF(Customer_Dim[[#This Row],[Age]]<=60,"Middle-Aged","Senior"))) -> Middle-Aged
A6: CUST1004 | B6: Caroline Collins | C6: =PROPER(B6) -> Caroline Collins | D6: =TRIM(C6) -> Caroline Collins | E6: 64 | F6: Female | G6: Nicholasshire | H6: California | I6: USA | J6: Silver | K6: =IF(ISBLANK(J6),"UNKNOWN",J6) -> Silver | L6: =IF(Customer_Dim[[#This Row],[Age]]<25,"Youth", IF(Customer_Dim[[#This Row],[Age]]<=40,"Adult", IF(Customer_Dim[[#This Row],[Age]]<=60,"Middle-Aged","Senior"))) -> Senior
A7: CUST1005 | B7: Christine Vaughn | C7: =PROPER(B7) -> Christine Vaughn | D7: =TRIM(C7) -> Christine Vaughn | E7: 24 | F7: Male | G7: East Amandamouth | H7: Oregon | I7: USA | J7: Bronze | K7: =IF(ISBLANK(J7),"UNKNOWN",J7) -> Bronze | L7: =IF(Customer_Dim[[#This Row],[Age]]<25,"Youth", IF(Customer_Dim[[#This Row],[Age]]<=40,"Adult", IF(Customer_Dim[[#This Row],[Age]]<=60,"Middle-Aged","Senior"))) -> Youth
A8: CUST1006 | B8: Amber Jackson | C8: =PROPER(B8) -> Amber Jackson | D8: =TRIM(C8) -> Amber Jackson | E8: 29 | F8: Female | G8: Deborahborough | H8: South Dakota | I8: USA | J8: Platinum | K8: =IF(ISBLANK(J8),"UNKNOWN",J8) -> Platinum | L8: =IF(Customer_Dim[[#This Row],[Age]]<25,"Youth", IF(Customer_Dim[[#This Row],[Age]]<=40,"Adult", IF(Customer_Dim[[#This Row],[Age]]<=60,"Middle-Aged","Senior"))) -> Adult
A9: CUST1007 | B9: Daniel Boyd | C9: =PROPER(B9) -> Daniel Boyd | D9: =TRIM(C9) -> Daniel Boyd | E9: 29 | F9: Female | G9: West Pamelafurt | H9: West Virginia | I9: USA | J9: Bronze | K9: =IF(ISBLANK(J9),"UNKNOWN",J9) -> Bronze | L9: =IF(Customer_Dim[[#This Row],[Age]]<25,"Youth", IF(Customer_Dim[[#This Row],[Age]]<=40,"Adult", IF(Customer_Dim[[#This Row],[Age]]<=60,"Middle-Aged","Senior"))) -> Adult
A10: CUST1008 | B10: Melissa Howard | C10: =PROPER(B10) -> Melissa Howard | D10: =TRIM(C10) -> Melissa Howard | E10: 53 | F10: Female | G10: Maynardton | H10: New Hampshire | I10: USA | J10: Gold | K10: =IF(ISBLANK(J10),"UNKNOWN",J10) -> Gold | L10: =IF(Customer_Dim[[#This Row],[Age]]<25,"Youth", IF(Customer_Dim[[#This Row],[Age]]<=40,"Adult", IF(Customer_Dim[[#This Row],[Age]]<=60,"Middle-Aged","Senior"))) -> Middle-Aged
A11: CUST1009 | B11: Ms. Maria Leach | C11: =PROPER(B11) -> Ms. Maria Leach | D11: =TRIM(C11) -> Ms. Maria Leach | E11: 64 | F11: Male | G11: Melissashire | H11: Pennsylvania | I11: USA | J11: Platinum | K11: =IF(ISBLANK(J11),"UNKNOWN",J11) -> Platinum | L11: =IF(Customer_Dim[[#This Row],[Age]]<25,"Youth", IF(Customer_Dim[[#This Row],[Age]]<=40,"Adult", IF(Customer_Dim[[#This Row],[Age]]<=60,"Middle-Aged","Senior"))) -> Senior
A12: CUST1010 | B12: Dominic Page | C12: =PROPER(B12) -> Dominic Page | D12: =TRIM(C12) -> Dominic Page | E12: 53 | F12: Male | G12: Port Michaelburgh | H12: Pennsylvania | I12: USA | J12: Bronze | K12: =IF(ISBLANK(J12),"UNKNOWN",J12) -> Bronze | L12: =IF(Customer_Dim[[#This Row],[Age]]<25,"Youth", IF(Customer_Dim[[#This Row],[Age]]<=40,"Adult", IF(Customer_Dim[[#This Row],[Age]]<=60,"Middle-Aged","Senior"))) -> Middle-Aged
A13: CUST1011 | B13: Brian Lopez | C13: =PROPER(B13) -> Brian Lopez | D13: =TRIM(C13) -> Brian Lopez | E13: 28 | F13: Female | G13: East Krista | H13: New York | I13: USA | J13: Gold | K13: =IF(ISBLANK(J13),"UNKNOWN",J13) -> Gold | L13: =IF(Customer_Dim[[#This Row],[Age]]<25,"Youth", IF(Customer_Dim[[#This Row],[Age]]<=40,"Adult", IF(Customer_Dim[[#This Row],[Age]]<=60,"Middle-Aged","Senior"))) -> Adult
A14: CUST1012 | B14: Kenneth Lambert | C14: =PROPER(B14) -> Kenneth Lambert | D14: =TRIM(C14) -> Kenneth Lambert | E14: 55 | F14: Female | G14: North Kathryn | H14: Kansas | I14: USA | J14: Platinum | K14: =IF(ISBLANK(J14),"UNKNOWN",J14) -> Platinum | L14: =IF(Customer_Dim[[#This Row],[Age]]<25,"Youth", IF(Customer_Dim[[#This Row],[Age]]<=40,"Adult", IF(Customer_Dim[[#This Row],[Age]]<=60,"Middle-Aged","Senior"))) -> Middle-Aged
... A19: CUST1017 | B19: Adam Cruz | C19: =PROPER(B19) -> Adam Cruz | D19: =TRIM(C19) -> Adam Cruz | E19: 60 | F19: Female | G19: Brandonville | H19: Georgia | I19: USA | J19: Platinum | K19: =IF(ISBLANK(J19),"UNKNOWN",J19) -> Platinum | L19: =IF(Customer_Dim[[#This Row],[Age]]<25,"Youth", IF(Customer_Dim[[#This Row],[Age]]<=40,"Adult", IF(Customer_Dim[[#This Row],[Age]]<=60,"Middle-Aged","Senior"))) -> Middle-Aged
A20: CUST1018 | B20: Rhonda Moss | C20: =PROPER(B20) -> Rhonda Moss | D20: =TRIM(C20) -> Rhonda Moss | E20: 43 | F20: Male | G20: South William | H20: Kansas | I20: USA | K20: =IF(ISBLANK(J20),"UNKNOWN",J20) -> UNKNOWN | L20: =IF(Customer_Dim[[#This Row],[Age]]<25,"Youth", IF(Customer_Dim[[#This Row],[Age]]<=40,"Adult", IF(Customer_Dim[[#This Row],[Age]]<=60,"Middle-Aged","Senior"))) -> Middle-Aged
A21: CUST1019 | B21: Michael Torres | C21: =PROPER(B21) -> Michael Torres | D21: =TRIM(C21) -> Michael Torres | E21: 46 | F21: Female | G21: Gonzalezfort | H21: New Jersey | I21: USA | J21: Platinum | K21: =IF(ISBLANK(J21),"UNKNOWN",J21) -> Platinum | L21: =IF(Customer_Dim[[#This Row],[Age]]<25,"Youth", IF(Customer_Dim[[#This Row],[Age]]<=40,"Adult", IF(Customer_Dim[[#This Row],[Age]]<=60,"Middle-Aged","Senior"))) -> Middle-Aged
A22: CUST1020 | B22: Bridget Allen | C22: =PROPER(B22) -> Bridget Allen | D22: =TRIM(C22) -> Bridget Allen | E22: 59 | F22: Male | G22: Lake Shaneburgh | H22: Delaware | I22: USA | J22: Silver | K22: =IF(ISBLANK(J22),"UNKNOWN",J22) -> Silver | L22: =IF(Customer_Dim[[#This Row],[Age]]<25,"Youth", IF(Customer_Dim[[#This Row],[Age]]<=40,"Adult", IF(Customer_Dim[[#This Row],[Age]]<=60,"Middle-Aged","Senior"))) -> Middle-Aged
A23: CUST1021 | B23: Jeff Martinez | C23: =PROPER(B23) -> Jeff Martinez | D23: =TRIM(C23) -> Jeff Martinez | E23: 36 | F23: Female | G23: Smithburgh | H23: Oklahoma | I23: USA | J23: Gold | K23: =IF(ISBLANK(J23),"UNKNOWN",J23) -> Gold | L23: =IF(Customer_Dim[[#This Row],[Age]]<25,"Youth", IF(Customer_Dim[[#This Row],[Age]]<=40,"Adult", IF(Customer_Dim[[#This Row],[Age]]<=60,"Middle-Aged","Senior"))) -> Adult
A24: CUST1022 | B24: paul fox | C24: =PROPER(B24) -> Paul Fox | D24: =TRIM(C24) -> Paul Fox | E24: 33 | F24: Female | G24: Michaelton | H24: Hawaii | I24: USA | J24: Silver | K24: =IF(ISBLANK(J24),"UNKNOWN",J24) -> Silver | L24: =IF(Customer_Dim[[#This Row],[Age]]<25,"Youth", IF(Customer_Dim[[#This Row],[Age]]<=40,"Adult", IF(Customer_Dim[[#This Row],[Age]]<=60,"Middle-Aged","Senior"))) -> Adult
A25: CUST1023 | B25: Jonathan Steele | C25: =PROPER(B25) -> Jonathan Steele | D25: =TRIM(C25) -> Jonathan Steele | E25: 52 | F25: Female | G25: Molinabury | H25: Oregon | I25: USA | J25: Silver | K25: =IF(ISBLANK(J25),"UNKNOWN",J25) -> Silver | L25: =IF(Customer_Dim[[#This Row],[Age]]<25,"Youth", IF(Customer_Dim[[#This Row],[Age]]<=40,"Adult", IF(Customer_Dim[[#This Row],[Age]]<=60,"Middle-Aged","Senior"))) -> Middle-Aged
A26: CUST1024 | B26: Heather Collins | C26: =PROPER(B26) -> Heather Collins | D26: =TRIM(C26) -> Heather Collins | E26: 40 | F26: Male | G26: Rogerschester | H26: Idaho | I26: USA | J26: Platinum | K26: =IF(ISBLANK(J26),"UNKNOWN",J26) -> Platinum | L26: =IF(Customer_Dim[[#This Row],[Age]]<25,"Youth", IF(Customer_Dim[[#This Row],[Age]]<=40,"Adult", IF(Customer_Dim[[#This Row],[Age]]<=60,"Middle-Aged","Senior"))) -> Adult
A27: CUST1025 | B27: Diana Taylor | C27: =PROPER(B27) -> Diana Taylor | D27: =TRIM(C27) -> Diana Taylor | E27: 59 | F27: Female | G27: Vasqueztown | H27: California | I27: USA | J27: Bronze | K27: =IF(ISBLANK(J27),"UNKNOWN",J27) -> Bronze | L27: =IF(Customer_Dim[[#This Row],[Age]]<25,"Youth", IF(Customer_Dim[[#This Row],[Age]]<=40,"Adult", IF(Customer_Dim[[#This Row],[Age]]<=60,"Middle-Aged","Senior"))) -> Middle-Aged
A28: CUST1026 | B28: Amber Carlson | C28: =PROPER(B28) -> Amber Carlson | D28: =TRIM(C28) -> Amber Carlson | E28: 18 | F28: Female | G28: East Michellemouth | H28: Missouri | I28: USA | J28: Gold | K28: =IF(ISBLANK(J28),"UNKNOWN",J28) -> Gold | L28: =IF(Customer_Dim[[#This Row],[Age]]<25,"Youth", IF(Customer_Dim[[#This Row],[Age]]<=40,"Adult", IF(Customer_Dim[[#This Row],[Age]]<=60,"Middle-Aged","Senior"))) -> Youth
A29: CUST1027 | B29: Leslie Johnson | C29: =PROPER(B29) -> Leslie Johnson | D29: =TRIM(C29) -> Leslie Johnson | E29: 31 | F29: Male | G29: Mollyshire | H29: Utah | I29: USA | K29: =IF(ISBLANK(J29),"UNKNOWN",J29) -> UNKNOWN | L29: =IF(Customer_Dim[[#This Row],[Age]]<25,"Youth", IF(Customer_Dim[[#This Row],[Age]]<=40,"Adult", IF(Customer_Dim[[#This Row],[Age]]<=60,"Middle-Aged","Senior"))) -> Adult
A30: CUST1028 | B30: Joshua Ryan | C30: =PROPER(B30) -> Joshua Ryan | D30: =TRIM(C30) -> Joshua Ryan | E30: 27 | F30: Female | G30: New David | H30: New Jersey | I30: USA | J30: Platinum | K30: =IF(ISBLANK(J30),"UNKNOWN",J30) -> Platinum | L30: =IF(Customer_Dim[[#This Row],[Age]]<25,"Youth", IF(Customer_Dim[[#This Row],[Age]]<=40,"Adult", IF(Customer_Dim[[#This Row],[Age]]<=60,"Middle-Aged","Senior"))) -> Adult
A31: CUST1029 | B31: David Arnold | C31: =PROPER(B31) -> David Arnold | D31: =TRIM(C31) -> David Arnold | E31: 54 | F31: Female | G31: East Jennifer | H31: California | I31: USA | J31: Silver | K31: =IF(ISBLANK(J31),"UNKNOWN",J31) -> Silver | L31: =IF(Customer_Dim[[#This Row],[Age]]<25,"Youth", IF(Customer_Dim[[#This Row],[Age]]<=40,"Adult", IF(Customer_Dim[[#This Row],[Age]]<=60,"Middle-Aged","Senior"))) -> Middle-Aged
A32: CUST1030 | B32: Jessica Acevedo | C32: =PROPER(B32) -> Jessica Acevedo | D32: =TRIM(C32) -> Jessica Acevedo | E32: 64 | F32: Female | G32: Amybury | H32: Pennsylvania | I32: USA | J32: Bronze | K32: =IF(ISBLANK(J32),"UNKNOWN",J32) -> Bronze | L32: =IF(Customer_Dim[[#This Row],[Age]]<25,"Youth", IF(Customer_Dim[[#This Row],[Age]]<=40,"Adult", IF(Customer_Dim[[#This Row],[Age]]<=60,"Middle-Aged","Senior"))) -> Senior
A33: CUST1031 | B33: Sarah Vance | C33: =PROPER(B33) -> Sarah Vance | D33: =TRIM(C33) -> Sarah Vance | E33: 41 | F33: Male | G33: Johnsonville | H33: Oregon | I33: USA | J33: Silver | K33: =IF(ISBLANK(J33),"UNKNOWN",J33) -> Silver | L33: =IF(Customer_Dim[[#This Row],[Age]]<25,"Youth", IF(Customer_Dim[[#This Row],[Age]]<=40,"Adult", IF(Customer_Dim[[#This Row],[Age]]<=60,"Middle-Aged","Senior"))) -> Middle-Aged
A34: CUST1032 | B34: Mike Jennings | C34: =PROPER(B34) -> Mike Jennings | D34: =TRIM(C34) -> Mike Jennings | E34: 48 | F34: Female | G34: Fostermouth | H34: Arizona | I34: USA | J34: Gold | K34: =IF(ISBLANK(J34),"UNKNOWN",J34) -> Gold | L34: =IF(Customer_Dim[[#This Row],[Age]]<25,"Youth", IF(Customer_Dim[[#This Row],[Age]]<=40,"Adult", IF(Customer_Dim[[#This Row],[Age]]<=60,"Middle-Aged","Senior"))) -> Middle-Aged
A35: CUST1033 | B35: Robert Jones DDS | C35: =PROPER(B35) -> Robert Jones Dds | D35: =TRIM(C35) -> Robert Jones Dds | E35: 25 | F35: Male | G35: Tristanton | H35: Oklahoma | I35: USA | J35: Platinum | K35: =IF(ISBLANK(J35),"UNKNOWN",J35) -> Platinum | L35: =IF(Customer_Dim[[#This Row],[Age]]<25,"Youth", IF(Customer_Dim[[#This Row],[Age]]<=40,"Adult", IF(Customer_Dim[[#This Row],[Age]]<=60,"Middle-Aged","Senior"))) -> Adult
A36: CUST1034 | B36: Christopher Olson | C36: =PROPER(B36) -> Christopher Olson | D36: =TRIM(C36) -> Christopher Olson | E36: 27 | F36: Female | G36: West Richard | H36: Maryland | I36: USA | J36: Platinum | K36: =IF(ISBLANK(J36),"UNKNOWN",J36) -> Platinum | L36: =IF(Customer_Dim[[#This Row],[Age]]<25,"Youth", IF(Customer_Dim[[#This Row],[Age]]<=40,"Adult", IF(Customer_Dim[[#This Row],[Age]]<=60,"Middle-Aged","Senior"))) -> Adult
A37: CUST1035 | B37: Rachel Myers | C37: =PROPER(B37) -> Rachel Myers | D37: =TRIM(C37) -> Rachel Myers | E37: 52 | F37: Male | G37: Robertberg | H37: North Dakota | I37: USA | J37: Silver | K37: =IF(ISBLANK(J37),"UNKNOWN",J37) -> Silver | L37: =IF(Customer_Dim[[#This Row],[Age]]<25,"Youth", IF(Customer_Dim[[#This Row],[Age]]<=40,"Adult", IF(Customer_Dim[[#This Row],[Age]]<=60,"Middle-Aged","Senior"))) -> Middle-Aged
A38: CUST1036 | B38: Thomas Phillips | C38: =PROPER(B38) -> Thomas Phillips | D38: =TRIM(C38) -> Thomas Phillips | E38: 20 | F38: Female | G38: Luisfurt | H38: Georgia | I38: USA | J38: Gold | K38: =IF(ISBLANK(J38),"UNKNOWN",J38) -> Gold | L38: =IF(Customer_Dim[[#This Row],[Age]]<25,"Youth", IF(Customer_Dim[[#This Row],[Age]]<=40,"Adult", IF(Customer_Dim[[#This Row],[Age]]<=60,"Middle-Aged","Senior"))) -> Youth
A39: CUST1037 | B39: Christopher Carter | C39: =PROPER(B39) -> Christopher Carter | D39: =TRIM(C39) -> Christopher Carter | E39: 27 | F39: Female | G39: Brendastad | H39: South Dakota | I39: USA | K39: =IF(ISBLANK(J39),"UNKNOWN",J39) -> UNKNOWN | L39: =IF(Customer_Dim[[#This Row],[Age]]<25,"Youth", IF(Customer_Dim[[#This Row],[Age]]<=40,"Adult", IF(Customer_Dim[[#This Row],[Age]]<=60,"Middle-Aged","Senior"))) -> Adult
A40: CUST1038 | B40: Deanna Simpson | C40: =PROPER(B40) -> Deanna Simpson | D40: =TRIM(C40) -> Deanna Simpson | E40: 35 | F40: Female | G40: Brownport | H40: North Dakota | I40: USA | J40: Bronze | K40: =IF(ISBLANK(J40),"UNKNOWN",J40) -> Bronze | L40: =IF(Customer_Dim[[#This Row],[Age]]<25,"Youth", IF(Customer_Dim[[#This Row],[Age]]<=40,"Adult", IF(Customer_Dim[[#This Row],[Age]]<=60,"Middle-Aged","Senior"))) -> Adult
A41: CUST1039 | B41: Tonya Reynolds | C41: =PROPER(B41) -> Tonya Reynolds | D41: =TRIM(C41) -> Tonya Reynolds | E41: 55 | F41: Female | G41: Darleneton | H41: Michigan | I41: USA | J41: Gold | K41: =IF(ISBLANK(J41),"UNKNOWN",J41) -> Gold | L41: =IF(Customer_Dim[[#This Row],[Age]]<25,"Youth", IF(Customer_Dim[[#This Row],[Age]]<=40,"Adult", IF(Customer_Dim[[#This Row],[Age]]<=60,"Middle-Aged","Senior"))) -> Middle-Aged
A42: CUST1040 | B42: Eric Vega | C42: =PROPER(B42) -> Eric Vega | D42: =TRIM(C42) -> Eric Vega | E42: 50 | F42: Male | G42: Williamsonland | H42: Kansas | I42: USA | J42: Gold | K42: =IF(ISBLANK(J42),"UNKNOWN",J42) -> Gold | L42: =IF(Customer_Dim[[#This Row],[Age]]<25,"Youth", IF(Customer_Dim[[#This Row],[Age]]<=40,"Adult", IF(Customer_Dim[[#This Row],[Age]]<=60,"Middle-Aged","Senior"))) -> Middle-Aged
A43: CUST1041 | B43: James Gibbs | C43: =PROPER(B43) -> James Gibbs | D43: =TRIM(C43) -> James Gibbs | E43: 21 | F43: Male | G43: Mooneyshire | H43: Alaska | I43: USA | J43: Platinum | K43: =IF(ISBLANK(J43),"UNKNOWN",J43) -> Platinum | L43: =IF(Customer_Dim[[#This Row],[Age]]<25,"Youth", IF(Customer_Dim[[#This Row],[Age]]<=40,"Adult", IF(Customer_Dim[[#This Row],[Age]]<=60,"Middle-Aged","Senior"))) -> Youth
A44: CUST1042 | B44: William Martin | C44: =PROPER(B44) -> William Martin | D44: =TRIM(C44) -> William Martin | E44: 19 | F44: Male | G44: Ryanburgh | H44: Connecticut | I44: USA | J44: Platinum | K44: =IF(ISBLANK(J44),"UNKNOWN",J44) -> Platinum | L44: =IF(Customer_Dim[[#This Row],[Age]]<25,"Youth", IF(Customer_Dim[[#This Row],[Age]]<=40,"Adult", IF(Customer_Dim[[#This Row],[Age]]<=60,"Middle-Aged","Senior"))) -> Youth
A45: CUST1043 | B45: Joseph Snow | C45: =PROPER(B45) -> Joseph Snow | D45: =TRIM(C45) -> Joseph Snow | E45: 45 | F45: Male | G45: South Michaelfort | H45: Vermont | I45: USA | J45: Gold | K45: =IF(ISBLANK(J45),"UNKNOWN",J45) -> Gold | L45: =IF(Customer_Dim[[#This Row],[Age]]<25,"Youth", IF(Customer_Dim[[#This Row],[Age]]<=40,"Adult", IF(Customer_Dim[[#This Row],[Age]]<=60,"Middle-Aged","Senior"))) -> Middle-Aged
A46: CUST1044 | B46: Denise Williams | C46: =PROPER(B46) -> Denise Williams | D46: =TRIM(C46) -> Denise Williams | E46: 34 | F46: Male | G46: Christianstad | H46: Hawaii | I46: USA | J46: Bronze | K46: =IF(ISBLANK(J46),"UNKNOWN",J46) -> Bronze | L46: =IF(Customer_Dim[[#This Row],[Age]]<25,"Youth", IF(Customer_Dim[[#This Row],[Age]]<=40,"Adult", IF(Customer_Dim[[#This Row],[Age]]<=60,"Middle-Aged","Senior"))) -> Adult
A47: CUST1045 | B47: Jordan Jackson DDS | C47: =PROPER(B47) -> Jordan Jackson Dds | D47: =TRIM(C47) -> Jordan Jackson Dds | E47: 54 | F47: Male | G47: North Johnview | H47: Arizona | I47: USA | J47: Gold | K47: =IF(ISBLANK(J47),"UNKNOWN",J47) -> Gold | L47: =IF(Customer_Dim[[#This Row],[Age]]<25,"Youth", IF(Customer_Dim[[#This Row],[Age]]<=40,"Adult", IF(Customer_Dim[[#This Row],[Age]]<=60,"Middle-Aged","Senior"))) -> Middle-Aged
A48: CUST1046 | B48: Michelle Garcia DDS | C48: =PROPER(B48) -> Michelle Garcia Dds | D48: =TRIM(C48) -> Michelle Garcia Dds | E48: 55 | F48: Female | G48: Perezbury | H48: Ohio | I48: USA | J48: Platinum | K48: =IF(ISBLANK(J48),"UNKNOWN",J48) -> Platinum | L48: =IF(Customer_Dim[[#This Row],[Age]]<25,"Youth", IF(Customer_Dim[[#This Row],[Age]]<=40,"Adult", IF(Customer_Dim[[#This Row],[Age]]<=60,"Middle-Aged","Senior"))) -> Middle-Aged
A49: CUST1047 | B49: Gina Knight | C49: =PROPER(B49) -> Gina Knight | D49: =TRIM(C49) -> Gina Knight | E49: 54 | F49: Female | G49: Lake Roberthaven | H49: Nevada | I49: USA | J49: Silver | K49: =IF(ISBLANK(J49),"UNKNOWN",J49) -> Silver | L49: =IF(Customer_Dim[[#This Row],[Age]]<25,"Youth", IF(Customer_Dim[[#This Row],[Age]]<=40,"Adult", IF(Customer_Dim[[#This Row],[Age]]<=60,"Middle-Aged","Senior"))) -> Middle-Aged
A50: CUST1048 | B50: April Mullins | C50: =PROPER(B50) -> April Mullins | D50: =TRIM(C50) -> April Mullins | E50: 54 | F50: Male | G50: Dawsonbury | H50: North Carolina | I50: USA | J50: Platinum | K50: =IF(ISBLANK(J50),"UNKNOWN",J50) -> Platinum | L50: =IF(Customer_Dim[[#This Row],[Age]]<25,"Youth", IF(Customer_Dim[[#This Row],[Age]]<=40,"Adult", IF(Customer_Dim[[#This Row],[Age]]<=60,"Middle-Aged","Senior"))) -> Middle-Aged
A51: CUST1049 | B51: Timothy Weaver | C51: =PROPER(B51) -> Timothy Weaver | D51: =TRIM(C51) -> Timothy Weaver | E51: 45 | F51: Female | G51: New Amy | H51: Ohio | I51: USA | J51: Gold | K51: =IF(ISBLANK(J51),"UNKNOWN",J51) -> Gold | L51: =IF(Customer_Dim[[#This Row],[Age]]<25,"Youth", IF(Customer_Dim[[#This Row],[Age]]<=40,"Adult", IF(Customer_Dim[[#This Row],[Age]]<=60,"Middle-Aged","Senior"))) -> Middle-Aged
... A501: C-1499 | B501: Philip Pennington | C501: =PROPER(B501) -> Philip Pennington | D501: =TRIM(C501) -> Philip Pennington | E501: 27 | F501: Female | G501: East Valerieview | H501: Oregon | I501: USA | J501: Platinum | K501: =IF(ISBLANK(J501),"UNKNOWN",J501) -> Platinum | L501: =IF(Customer_Dim[[#This Row],[Age]]<25,"Youth", IF(Customer_Dim[[#This Row],[Age]]<=40,"Adult", IF(Customer_Dim[[#This Row],[Age]]<=60,"Middle-Aged","Senior"))) -> Adult

Sheet Product_Dim
A1: Product_ID | B1: Product_Name | C1: Category | D1: Sub_Category | E1: Brand | F1: Cost | G1: COST2 | H1: Stock | I1: Stock3
A2: PROD0 | B2: Brother Laser Printer | C2: Electronics | D2: Computer | E2: Hunt Inc | F2: 112.42 | G2: =IF(ISBLANK(F2),AVERAGE($F$2:$F$101),F2) -> 112.42 | H2: 416 | I2: =IF(ISBLANK(H2),MODE($H$2:$H$101),H2) -> 416
A3: PROD1 | B3: Men's Graphic T-Shirt | C3: Clothing | D3: Tops | E3: Terry-Moore | F3: 342.56 | G3: =IF(ISBLANK(F3),AVERAGE($F$2:$F$101),F3) -> 342.56 | H3: 181 | I3: =IF(ISBLANK(H3),MODE($H$2:$H$101),H3) -> 181
A4: PROD2 | B4: Women's Casual Hoodie | C4: Clothing | D4: Outerwear | E4: Sims Inc | G4: =IF(ISBLANK(F4),AVERAGE($F$2:$F$101),F4) -> 254.04362 | H4: 352 | I4: =IF(ISBLANK(H4),MODE($H$2:$H$101),H4) -> 352
A5: P-3 | B5: Men's Running Jacket | C5: Clothing | D5: Outerwear | E5: Pineda Ltd | F5: 364.67 | G5: =IF(ISBLANK(F5),AVERAGE($F$2:$F$101),F5) -> 364.67 | H5: 452 | I5: =IF(ISBLANK(H5),MODE($H$2:$H$101),H5) -> 452
A6: PROD4 | B6: Women's Yoga Pants | C6: Clothing | D6: Bottoms | E6: Gonzales-Davis | F6: 306.46 | G6: =IF(ISBLANK(F6),AVERAGE($F$2:$F$101),F6) -> 306.46 | H6: 487 | I6: =IF(ISBLANK(H6),MODE($H$2:$H$101),H6) -> 487
A7: PROD5 | B7: Men's Leather Belt | C7: Clothing | D7: Accessories | E7: Baldwin, Garza and Gonzalez | F7: 261 | G7: =IF(ISBLANK(F7),AVERAGE($F$2:$F$101),F7) -> 261 | H7: 59 | I7: =IF(ISBLANK(H7),MODE($H$2:$H$101),H7) -> 59
A8: PROD6 | B8: Herbal Face Moisturizer | C8: Beauty | D8: Skincare | E8: Davidson PLC | F8: 312.8 | G8: =IF(ISBLANK(F8),AVERAGE($F$2:$F$101),F8) -> 312.8 | H8: 350 | I8: =IF(ISBLANK(H8),MODE($H$2:$H$101),H8) -> 350
A9: PROD7 | B9: LED Table Lamp | C9: Home | D9: Lighting | E9: Harrell LLC | F9: 218.86 | G9: =IF(ISBLANK(F9),AVERAGE($F$2:$F$101),F9) -> 218.86 | H9: 170 | I9: =IF(ISBLANK(H9),MODE($H$2:$H$101),H9) -> 170
A10: PROD8 | B10: Wireless Bluetooth Earbuds | C10: Electronics | D10: Audio | E10: Perez-Johnston | F10: 439.07 | G10: =IF(ISBLANK(F10),AVERAGE($F$2:$F$101),F10) -> 439.07 | H10: 142 | I10: =IF(ISBLANK(H10),MODE($H$2:$H$101),H10) -> 142
A11: PROD9 | B11: Adjustable Dumbbell Set | C11: Sports | D11: Fitness | E11: Hill PLC | F11: 495.72 | G11: =IF(ISBLANK(F11),AVERAGE($F$2:$F$101),F11) -> 495.72 | H11: 323 | I11: =IF(ISBLANK(H11),MODE($H$2:$H$101),H11) -> 323
A12: PROD10 | B12: Ceramic Kitchen Bowl Set | C12: Home | D12: Kitchen | E12: Hamilton Group | F12: 298.86 | G12: =IF(ISBLANK(F12),AVERAGE($F$2:$F$101),F12) -> 298.86 | H12: 308 | I12: =IF(ISBLANK(H12),MODE($H$2:$H$101),H12) -> 308
A13: PROD11 | B13: HD Smart TV Stick | C13: Electronics | D13: Accessories | E13: Gibson, Hobbs and Weaver | F13: 449.4 | G13: =IF(ISBLANK(F13),AVERAGE($F$2:$F$101),F13) -> 449.4 | I13: =IF(ISBLANK(H13),MODE($H$2:$H$101),H13) -> 82
A14: PROD12 | B14: Hair Strengthening Shampoo | C14: Beauty | D14: Haircare | E14: Rice LLC | F14: 115.82 | G14: =IF(ISBLANK(F14),AVERAGE($F$2:$F$101),F14) -> 115.82 | H14: 460 | I14: =IF(ISBLANK(H14),MODE($H$2:$H$101),H14) -> 460
A15: PROD13 | B15: USB-C Fast Charger | C15: Electronics | D15: Accessories | E15: Dawson-Perkins | F15: 242.23 | G15: =IF(ISBLANK(F15),AVERAGE($F$2:$F$101),F15) -> 242.23 | H15: 453 | I15: =IF(ISBLANK(H15),MODE($H$2:$H$101),H15) -> 453
A16: PROD14 | B16: Decorative Wall Mirror | C16: Home | D16: Decor | E16: Luna, Anderson and Bowman | F16: 48.01 | G16: =IF(ISBLANK(F16),AVERAGE($F$2:$F$101),F16) -> 48.01 | H16: 439 | I16: =IF(ISBLANK(H16),MODE($H$2:$H$101),H16) -> 439
A17: PROD15 | B17: 4K Home Projector | C17: Electronics | D17: Appliances | E17: Thomas LLC | F17: 465.34 | G17: =IF(ISBLANK(F17),AVERAGE($F$2:$F$101),F17) -> 465.34 | H17: 301 | I17: =IF(ISBLANK(H17),MODE($H$2:$H$101),H17) -> 301
A18: P-16 | B18: Beard Grooming Kit | C18: Beauty | D18: Grooming | E18: Erickson-Green | F18: 337.42 | G18: =IF(ISBLANK(F18),AVERAGE($F$2:$F$101),F18) -> 337.42 | H18: 256 | I18: =IF(ISBLANK(H18),MODE($H$2:$H$101),H18) -> 256
A19: PROD17 | B19: Soccer Training Cone Set | C19: Sports | D19: Accessories | E19: Ford, Murphy and Wilson | F19: 144.53 | G19: =IF(ISBLANK(F19),AVERAGE($F$2:$F$101),F19) -> 144.53 | H19: 367 | I19: =IF(ISBLANK(H19),MODE($H$2:$H$101),H19) -> 367
A20: PROD18 | B20: Women's Denim Jeans | C20: Clothing | D20: Bottoms | E20: Guerra-Hendrix | G20: =IF(ISBLANK(F20),AVERAGE($F$2:$F$101),F20) -> 254.04362 | H20: 343 | I20: =IF(ISBLANK(H20),MODE($H$2:$H$101),H20) -> 343
A21: PROD19 | B21: Knee Support Brace | C21: Sports | D21: Equipment | E21: May-Reese | F21: 21.34 | G21: =IF(ISBLANK(F21),AVERAGE($F$2:$F$101),F21) -> 21.34 | H21: 65 | I21: =IF(ISBLANK(H21),MODE($H$2:$H$101),H21) -> 65
A22: PROD20 | B22: Outdoor Sports Water Bottle | C22: Sports | D22: Accessories | E22: Soto-Ellis | F22: 131.51 | G22: =IF(ISBLANK(F22),AVERAGE($F$2:$F$101),F22) -> 131.51 | I22: =IF(ISBLANK(H22),MODE($H$2:$H$101),H22) -> 82
A23: PROD21 | B23: Multi-Purpose Storage Box | C23: Home | D23: Storage | E23: Gardner-Montes | F23: 123.46 | G23: =IF(ISBLANK(F23),AVERAGE($F$2:$F$101),F23) -> 123.46 | H23: 76 | I23: =IF(ISBLANK(H23),MODE($H$2:$H$101),H23) -> 76
A24: PROD22 | B24: Carbon Fiber Tennis Racket | C24: Sports | D24: Equipment | E24: Flores, Pineda and Rodriguez | F24: 484.62 | G24: =IF(ISBLANK(F24),AVERAGE($F$2:$F$101),F24) -> 484.62 | H24: 432 | I24: =IF(ISBLANK(H24),MODE($H$2:$H$101),H24) -> 432
A25: PROD23 | B25: Men's Formal Shirt | C25: Clothing | D25: Tops | E25: Moon, Mora and Santos | G25: =IF(ISBLANK(F25),AVERAGE($F$2:$F$101),F25) -> 254.04362 | H25: 360 | I25: =IF(ISBLANK(H25),MODE($H$2:$H$101),H25) -> 360
A26: PROD24 | B26: Foldable Camping Chair | C26: Sports | D26: Outdoor | E26: Cook Ltd | F26: 166.06 | G26: =IF(ISBLANK(F26),AVERAGE($F$2:$F$101),F26) -> 166.06 | H26: 340 | I26: =IF(ISBLANK(H26),MODE($H$2:$H$101),H26) -> 340
A27: PROD25 | B27: Women's Scarf Set | C27: Clothing | D27: Accessories | E27: Brown and Sons | F27: 174.02 | G27: =IF(ISBLANK(F27),AVERAGE($F$2:$F$101),F27) -> 174.02 | H27: 268 | I27: =IF(ISBLANK(H27),MODE($H$2:$H$101),H27) -> 268
A28: PROD26 | B28: Wireless Bluetooth Speaker | C28: Electronics | D28: Audio | E28: Reed-Schmidt | F28: 322.41 | G28: =IF(ISBLANK(F28),AVERAGE($F$2:$F$101),F28) -> 322.41 | H28: 213 | I28: =IF(ISBLANK(H28),MODE($H$2:$H$101),H28) -> 213
A29: PROD27 | B29: Decorative Floor Vase | C29: Home | D29: Decor | E29: Khan, Jones and Paul | G29: =IF(ISBLANK(F29),AVERAGE($F$2:$F$101),F29) -> 254.04362 | H29: 378 | I29: =IF(ISBLANK(H29),MODE($H$2:$H$101),H29) -> 378
A30: PROD28 | B30: Sports Stopwatch Timer | C30: Sports | D30: Accessories | E30: Burns-Hansen | F30: 38.76 | G30: =IF(ISBLANK(F30),AVERAGE($F$2:$F$101),F30) -> 38.76 | H30: 137 | I30: =IF(ISBLANK(H30),MODE($H$2:$H$101),H30) -> 137
A31: PROD29 | B31: Fabric Sofa Throw Blanket | C31: Home | D31: Decor | E31: Hoffman Group | F31: 218.48 | G31: =IF(ISBLANK(F31),AVERAGE($F$2:$F$101),F31) -> 218.48 | H31: 276 | I31: =IF(ISBLANK(H31),MODE($H$2:$H$101),H31) -> 276
A32: PROD30 | B32: Stainless Steel Cutlery Set | C32: Home | D32: Kitchen | E32: Stevens, Fernandez and Martin | F32: 19.52 | G32: =IF(ISBLANK(F32),AVERAGE($F$2:$F$101),F32) -> 19.52 | H32: 57 | I32: =IF(ISBLANK(H32),MODE($H$2:$H$101),H32) -> 57
A33: PROD31 | B33: Basketball | C33: Sports | D33: Team Sports | E33: Nolan-Snow | F33: 204.39 | G33: =IF(ISBLANK(F33),AVERAGE($F$2:$F$101),F33) -> 204.39 | H33: 281 | I33: =IF(ISBLANK(H33),MODE($H$2:$H$101),H33) -> 281
A34: PROD32 | B34: Vitamin C Face Serum | C34: Beauty | D34: Skincare | E34: Griffin Ltd | F34: 283.83 | G34: =IF(ISBLANK(F34),AVERAGE($F$2:$F$101),F34) -> 283.83 | H34: 244 | I34: =IF(ISBLANK(H34),MODE($H$2:$H$101),H34) -> 244
A35: PROD33 | B35: Modern Wall Clock | C35: Home | D35: Decor | E35: Weiss-Watson | F35: 179.77 | G35: =IF(ISBLANK(F35),AVERAGE($F$2:$F$101),F35) -> 179.77 | H35: 305 | I35: =IF(ISBLANK(H35),MODE($H$2:$H$101),H35) -> 305
A36: PROD34 | B36: Gaming Mechanical Keyboard | C36: Electronics | D36: Computer | E36: Lucero LLC | F36: 419.28 | G36: =IF(ISBLANK(F36),AVERAGE($F$2:$F$101),F36) -> 419.28 | H36: 86 | I36: =IF(ISBLANK(H36),MODE($H$2:$H$101),H36) -> 86
A37: PROD35 | B37: Bedroom Table Lamp | C37: Home | D37: Lighting | E37: Jones LLC | F37: 382.22 | G37: =IF(ISBLANK(F37),AVERAGE($F$2:$F$101),F37) -> 382.22 | H37: 329 | I37: =IF(ISBLANK(H37),MODE($H$2:$H$101),H37) -> 329
A38: PROD36 | B38: Women's Summer Dress | C38: Clothing | D38: Tops | E38: Smith-Mills | F38: 223.43 | G38: =IF(ISBLANK(F38),AVERAGE($F$2:$F$101),F38) -> 223.43 | H38: 154 | I38: =IF(ISBLANK(H38),MODE($H$2:$H$101),H38) -> 154
A39: PROD37 | B39: Men's Casual Sneakers | C39: Clothing | D39: Footwear | E39: Hogan-Lee | F39: 353.47 | G39: =IF(ISBLANK(F39),AVERAGE($F$2:$F$101),F39) -> 353.47 | H39: 214 | I39: =IF(ISBLANK(H39),MODE($H$2:$H$101),H39) -> 214
A40: PROD38 | B40: Sports Water Hydration Pack | C40: Sports | D40: Outdoor | E40: Sims-Smith | F40: 135.61 | G40: =IF(ISBLANK(F40),AVERAGE($F$2:$F$101),F40) -> 135.61 | H40: 394 | I40: =IF(ISBLANK(H40),MODE($H$2:$H$101),H40) -> 394
A41: PROD39 | B41: Portable Power Bank | C41: Electronics | D41: Mobile | E41: Cummings and Sons | F41: 326.06 | G41: =IF(ISBLANK(F41),AVERAGE($F$2:$F$101),F41) -> 326.06 | H41: 301 | I41: =IF(ISBLANK(H41),MODE($H$2:$H$101),H41) -> 301
... A48: PROD46 | B48: Men's Winter Jacket | C48: Clothing | D48: Outerwear | E48: Kelly, Smith and Perez | F48: 167.34 | G48: =IF(ISBLANK(F48),AVERAGE($F$2:$F$101),F48) -> 167.34 | H48: 296 | I48: =IF(ISBLANK(H48),MODE($H$2:$H$101),H48) -> 296
A49: PROD47 | B49: Makeup Brush Set | C49: Beauty | D49: Makeup | E49: Cook Inc | G49: =IF(ISBLANK(F49),AVERAGE($F$2:$F$101),F49) -> 254.04362 | H49: 431 | I49: =IF(ISBLANK(H49),MODE($H$2:$H$101),H49) -> 431
A50: PROD48 | B50: Car Dashboard Phone Holder | C50: Electronics | D50: Accessories | E50: Byrd, Stewart and Valdez | F50: 177.98 | G50: =IF(ISBLANK(F50),AVERAGE($F$2:$F$101),F50) -> 177.98 | H50: 103 | I50: =IF(ISBLANK(H50),MODE($H$2:$H$101),H50) -> 103
A51: PROD49 | B51: Men's Roll-On Perfume | C51: Beauty | D51: Fragrance | E51: Sullivan and Sons | F51: 43.29 | G51: =IF(ISBLANK(F51),AVERAGE($F$2:$F$101),F51) -> 43.29 | H51: 267 | I51: =IF(ISBLANK(H51),MODE($H$2:$H$101),H51) -> 267
A52: PROD50 | B52: Boxing Hand Wraps | C52: Sports | D52: Fitness | E52: Smith-King | F52: 190.29 | G52: =IF(ISBLANK(F52),AVERAGE($F$2:$F$101),F52) -> 190.29 | H52: 260 | I52: =IF(ISBLANK(H52),MODE($H$2:$H$101),H52) -> 260
A53: PROD51 | B53: HDMI Cable – 2m | C53: Electronics | D53: Accessories | E53: Bautista, Green and Hale | F53: 88.49 | G53: =IF(ISBLANK(F53),AVERAGE($F$2:$F$101),F53) -> 88.49 | H53: 246 | I53: =IF(ISBLANK(H53),MODE($H$2:$H$101),H53) -> 246
A54: PROD52 | B54: Rugby Ball | C54: Sports | D54: Team Sports | E54: Harris Inc | F54: 212.26 | G54: =IF(ISBLANK(F54),AVERAGE($F$2:$F$101),F54) -> 212.26 | H54: 82 | I54: =IF(ISBLANK(H54),MODE($H$2:$H$101),H54) -> 82
A55: PROD53 | B55: Men's Track Pants | C55: Clothing | D55: Bottoms | E55: Hamilton, Woods and Walker | F55: 386.56 | G55: =IF(ISBLANK(F55),AVERAGE($F$2:$F$101),F55) -> 386.56 | H55: 125 | I55: =IF(ISBLANK(H55),MODE($H$2:$H$101),H55) -> 125
A56: PROD54 | B56: Sports Stopwatch Pro | C56: Sports | D56: Accessories | E56: Thompson-French | F56: 434.84 | G56: =IF(ISBLANK(F56),AVERAGE($F$2:$F$101),F56) -> 434.84 | H56: 185 | I56: =IF(ISBLANK(H56),MODE($H$2:$H$101),H56) -> 185
A57: PROD55 | B57: Ceramic Plant Pot | C57: Home | D57: Decor | E57: Hatfield, Baird and Torres | F57: 81.75 | G57: =IF(ISBLANK(F57),AVERAGE($F$2:$F$101),F57) -> 81.75 | I57: =IF(ISBLANK(H57),MODE($H$2:$H$101),H57) -> 82
A58: PROD56 | B58: Premium Blanket Throw | C58: Home | D58: Decor | E58: Hernandez, Kennedy and Porter | F58: 461.47 | G58: =IF(ISBLANK(F58),AVERAGE($F$2:$F$101),F58) -> 461.47 | H58: 190 | I58: =IF(ISBLANK(H58),MODE($H$2:$H$101),H58) -> 190
A59: PROD57 | B59: Foam Roller | C59: Sports | D59: Fitness | E59: Atkinson, Camacho and Oliver | F59: 30.62 | G59: =IF(ISBLANK(F59),AVERAGE($F$2:$F$101),F59) -> 30.62 | H59: 138 | I59: =IF(ISBLANK(H59),MODE($H$2:$H$101),H59) -> 138
A60: PROD58 | B60: Womens Cotton Scarf | C60: Clothing | D60: Accessories | E60: Shepherd-Gould | F60: 113.83 | G60: =IF(ISBLANK(F60),AVERAGE($F$2:$F$101),F60) -> 113.83 | H60: 485 | I60: =IF(ISBLANK(H60),MODE($H$2:$H$101),H60) -> 485
A61: PROD59 | B61: Men's Hair Styling Gel | C61: Beauty | D61: Haircare | E61: Cline-Mccarthy | F61: 17.31 | G61: =IF(ISBLANK(F61),AVERAGE($F$2:$F$101),F61) -> 17.31 | H61: 399 | I61: =IF(ISBLANK(H61),MODE($H$2:$H$101),H61) -> 399
A62: PROD60 | B62: Luxury Perfume Spray | C62: Beauty | D62: Fragrance | E62: Gibson, Green and Lopez | F62: 482.75 | G62: =IF(ISBLANK(F62),AVERAGE($F$2:$F$101),F62) -> 482.75 | H62: 444 | I62: =IF(ISBLANK(H62),MODE($H$2:$H$101),H62) -> 444
A63: PROD61 | B63: Tennis Ball 3-Pack | C63: Sports | D63: Equipment | E63: Lopez LLC | F63: 103.45 | G63: =IF(ISBLANK(F63),AVERAGE($F$2:$F$101),F63) -> 103.45 | H63: 465 | I63: =IF(ISBLANK(H63),MODE($H$2:$H$101),H63) -> 465
A64: PROD62 | B64: Laptop Cooling Pad | C64: Electronics | D64: Computer | E64: Murray, Gould and Ware | F64: 86.42 | G64: =IF(ISBLANK(F64),AVERAGE($F$2:$F$101),F64) -> 86.42 | H64: 222 | I64: =IF(ISBLANK(H64),MODE($H$2:$H$101),H64) -> 222
A65: PROD63 | B65: Organic Sunscreen Lotion | C65: Beauty | D65: Skincare | E65: Anderson-Riley | F65: 266.86 | G65: =IF(ISBLANK(F65),AVERAGE($F$2:$F$101),F65) -> 266.86 | H65: 458 | I65: =IF(ISBLANK(H65),MODE($H$2:$H$101),H65) -> 458
A66: PROD64 | B66: Matte Lipstick Set | C66: Beauty | D66: Makeup | E66: Zhang Inc | F66: 299.11 | G66: =IF(ISBLANK(F66),AVERAGE($F$2:$F$101),F66) -> 299.11 | H66: 118 | I66: =IF(ISBLANK(H66),MODE($H$2:$H$101),H66) -> 118
A67: PROD65 | B67: Adjustable Dumbbells 20kg | C67: Sports | D67: Fitness | E67: Montgomery, Benton and Miller | F67: 240.63 | G67: =IF(ISBLANK(F67),AVERAGE($F$2:$F$101),F67) -> 240.63 | H67: 423 | I67: =IF(ISBLANK(H67),MODE($H$2:$H$101),H67) -> 423
A68: PROD66 | B68: Women's Hair Dryer Brush | C68: Beauty | D68: Haircare | E68: Torres, Spencer and Potter | F68: 340.39 | G68: =IF(ISBLANK(F68),AVERAGE($F$2:$F$101),F68) -> 340.39 | H68: 177 | I68: =IF(ISBLANK(H68),MODE($H$2:$H$101),H68) -> 177
A69: PROD67 | B69: Smart LED Light Strip | C69: Electronics | D69: Accessories | E69: Flores-Davis | F69: 349.17 | G69: =IF(ISBLANK(F69),AVERAGE($F$2:$F$101),F69) -> 349.17 | H69: 476 | I69: =IF(ISBLANK(H69),MODE($H$2:$H$101),H69) -> 476
... A84: PROD82 | B84: Fitness Resistance Bands | C84: Sports | D84: Fitness | E84: Reese-Watson | F84: 152.92 | G84: =IF(ISBLANK(F84),AVERAGE($F$2:$F$101),F84) -> 152.92 | H84: 281 | I84: =IF(ISBLANK(H84),MODE($H$2:$H$101),H84) -> 281
A85: PROD83 | B85: Hydrating Face Cleanser | C85: Beauty | D85: Skincare | E85: Butler Group | G85: =IF(ISBLANK(F85),AVERAGE($F$2:$F$101),F85) -> 254.04362 | H85: 159 | I85: =IF(ISBLANK(H85),MODE($H$2:$H$101),H85) -> 159
A86: PROD84 | B86: Wooden Bookshelf | C86: Home | D86: Furniture | E86: Collins-Stephenson | F86: 388.46 | G86: =IF(ISBLANK(F86),AVERAGE($F$2:$F$101),F86) -> 388.46 | H86: 208 | I86: =IF(ISBLANK(H86),MODE($H$2:$H$101),H86) -> 208
A87: PROD85 | B87: Women's Beanie Hat | C87: Clothing | D87: Accessories | E87: Richardson-Carrillo | F87: 119.57 | G87: =IF(ISBLANK(F87),AVERAGE($F$2:$F$101),F87) -> 119.57 | H87: 210 | I87: =IF(ISBLANK(H87),MODE($H$2:$H$101),H87) -> 210
A88: PROD86 | B88: Kitchen Cutting Board | C88: Home | D88: Kitchen | E88: Taylor, Dodson and Johnston | F88: 176.07 | G88: =IF(ISBLANK(F88),AVERAGE($F$2:$F$101),F88) -> 176.07 | H88: 82 | I88: =IF(ISBLANK(H88),MODE($H$2:$H$101),H88) -> 82
A89: PROD87 | B89: LED Bedside Lamp | C89: Home | D89: Lighting | E89: Aguilar, Horton and Lewis | F89: 371.38 | G89: =IF(ISBLANK(F89),AVERAGE($F$2:$F$101),F89) -> 371.38 | H89: 220 | I89: =IF(ISBLANK(H89),MODE($H$2:$H$101),H89) -> 220
A90: PROD88 | B90: Sports Wrist Sweatbands | C90: Sports | D90: Accessories | E90: Olsen-Daniels | F90: 131.24 | G90: =IF(ISBLANK(F90),AVERAGE($F$2:$F$101),F90) -> 131.24 | H90: 232 | I90: =IF(ISBLANK(H90),MODE($H$2:$H$101),H90) -> 232
A91: PROD89 | B91: Face Foundation Kit | C91: Beauty | D91: Makeup | E91: Taylor-Elliott | F91: 183.04 | G91: =IF(ISBLANK(F91),AVERAGE($F$2:$F$101),F91) -> 183.04 | H91: 457 | I91: =IF(ISBLANK(H91),MODE($H$2:$H$101),H91) -> 457
A92: PROD90 | B92: Gaming Mouse Pad XL | C92: Electronics | D92: Accessories | E92: Sharp, Taylor and Rodriguez | F92: 340.14 | G92: =IF(ISBLANK(F92),AVERAGE($F$2:$F$101),F92) -> 340.14 | H92: 361 | I92: =IF(ISBLANK(H92),MODE($H$2:$H$101),H92) -> 361
A93: PROD91 | B93: Women's High Heels | C93: Clothing | D93: Footwear | E93: Smith-Charles | F93: 438.25 | G93: =IF(ISBLANK(F93),AVERAGE($F$2:$F$101),F93) -> 438.25 | H93: 496 | I93: =IF(ISBLANK(H93),MODE($H$2:$H$101),H93) -> 496
A94: PROD92 | B94: Microwave Oven | C94: Home | D94: Appliances | E94: Green, Powell and Palmer | F94: 447.43 | G94: =IF(ISBLANK(F94),AVERAGE($F$2:$F$101),F94) -> 447.43 | H94: 191 | I94: =IF(ISBLANK(H94),MODE($H$2:$H$101),H94) -> 191
A95: PROD93 | B95: USB-C Laptop Charger | C95: Electronics | D95: Computer | E95: Martin LLC | F95: 377.52 | G95: =IF(ISBLANK(F95),AVERAGE($F$2:$F$101),F95) -> 377.52 | H95: 485 | I95: =IF(ISBLANK(H95),MODE($H$2:$H$101),H95) -> 485
A96: PROD94 | B96: Vitamin E Body Lotion | C96: Beauty | D96: Skincare | E96: Hoffman-Williams | F96: 358.47 | G96: =IF(ISBLANK(F96),AVERAGE($F$2:$F$101),F96) -> 358.47 | H96: 213 | I96: =IF(ISBLANK(H96),MODE($H$2:$H$101),H96) -> 213
A97: PROD95 | B97: Sports Stopwatch Basic | C97: Sports | D97: Accessories | E97: Wilson Group | F97: 60.65 | G97: =IF(ISBLANK(F97),AVERAGE($F$2:$F$101),F97) -> 60.65 | H97: 75 | I97: =IF(ISBLANK(H97),MODE($H$2:$H$101),H97) -> 75
... A101: PROD99 | B101: Stainless Steel Cookware Set | C101: Home | D101: Kitchen | E101: Campbell Ltd | F101: 201.41 | G101: =IF(ISBLANK(F101),AVERAGE($F$2:$F$101),F101) -> 201.41 | H101: 146 | I101: =IF(ISBLANK(H101),MODE($H$2:$H$101),H101) -> 146

Sheet Store_Dim
A1: Store_ID | B1: Store_Name | C1: Region | D1: City | E1: Store_Type
A2: STORE0 | B2: Rivera-Warner | C2: East | D2: Washingtonfurt | E2: Flagship
A3: STORE1 | B3: Martinez, Adkins and Johnson | C3: North | D3: Danielmouth | E3: Flagship
A4: STORE2 | B4: Black-Horn | C4: South | D4: North Nancyview | E4: Outlet
A5: STORE3 | B5: Johnson-Wright | C5: North | D5: Hoodberg | E5: Outlet
A6: STORE4 | B6: Alexander Group | C6: South | D6: Port Sharon | E6: Online
A7: STORE5 | B7: Gray Ltd | C7: North | D7: New Michaelchester | E7: Outlet
A8: STORE6 | B8: Benson-Elliott | C8: East | D8: Port Josephberg | E8: Online
A9: STORE7 | B9: Martinez-Mullins | C9: South | D9: Williamsfurt | E9: Online
A10: STORE8 | B10: Bean, Jones and Park | C10: West | D10: Thompsonborough | E10: Online
A11: STORE9 | B11: Moore, Padilla and Butler | C11: South | D11: East Johnstad | E11: Flagship
A12: STORE10 | B12: Hill, Wagner and Ballard | C12: East | D12: East Davidville | E12: Online
... A21: STORE19 | B21: Mann-Austin | C21: East | D21: Vasquezborough | E21: Online

Sheet Sheet9
A3: Row Labels | B3: Sum of Total Amount
A4: STORE0 | B4: 85138.555
A5: STORE1 | B5: 100344.57
A6: STORE10 | B6: 109791.72
A7: STORE11 | B7: 93048.141
A8: STORE12 | B8: 116829.22
A9: STORE13 | B9: 114592.72
A10: STORE14 | B10: 106248.28
A11: STORE15 | B11: 99679.086
A12: STORE16 | B12: 111704.94
A13: STORE17 | B13: 121555.11
A14: STORE18 | B14: 105447.24
A15: STORE19 | B15: 94225.723
... A24: Grand Total | B24: 2173363.4

Sheet Sales_Fact
A1: Sales_ID | B1: Order_Date | C1: Customer_ID | D1: Product_ID | E1: Store_ID | F1: Quantity | G1: Quantity1 | H1: Unit_Price | I1: UNIT Price | J1: Discount | K1: Discount2 | L1: Payment_Type | M1: Total_Amount | N1: Total Amount | O1: Loyalty Level | P1: Age | Q1: Gender | R1: Product category
A2: SALE0 | B2: 45480 | C2: CUST1409 | D2: PROD97 | E2: =TRIM(Sales_fact[[#This Row],[Store_ID]]) -> STORE3 | F2: 1 | G2: =IF(ISBLANK(F2),MODE($F$2:$F$2001),F2) -> 1 | H2: 218.04 | I2: =IF(ISBLANK(H2),AVERAGE($H$2:$H$2001),H2) -> 218.04 | J2: 0.09 | K2: =IF(ISBLANK(J2),MODE($J$2:$J$2001),J2) -> 0.09 | L2: Credit Card | M2: 198.4164 | N2: =G2*I2*(1-K2) -> 198.4164 | O2: =_xlfn.XLOOKUP(Sales_fact[[#This Row],[Customer_ID]],'Customer_Dim'!A:A,'Customer_Dim'!K:K,"Not Found") -> Gold | P2: =_xlfn.XLOOKUP(Sales_fact[[#This Row],[Customer_ID]],'Customer_Dim'!A:A, 'Customer_Dim'!E:E, "Not Found") -> 55 | Q2: =VLOOKUP(Sales_fact[[#This Row],[Customer_ID]], 'Customer_Dim'!A:F, 6, FALSE) -> Male | R2: =_xlfn.XLOOKUP(Sales_fact[[#This Row],[Product_ID]],Product_Dim!A:A,Product_Dim!C:C,"OTHERS") -> Sports | T2: Column1
A3: SALE1 | B3: 45285 | C3: CUST1467 | D3: PROD74 | E3: =TRIM(Sales_fact[[#This Row],[Store_ID]]) -> STORE17 | F3: 3 | G3: =IF(ISBLANK(F3),MODE($F$2:$F$2001),F3) -> 3 | H3: 104.47 | I3: =IF(ISBLANK(H3),AVERAGE($H$2:$H$2001),H3) -> 104.47 | J3: 0.27 | K3: =IF(ISBLANK(J3),MODE($J$2:$J$2001),J3) -> 0.27 | L3: PayPal | M3: 228.7893 | N3: =G3*I3*(1-K3) -> 228.7893 | O3: =_xlfn.XLOOKUP(Sales_fact[[#This Row],[Customer_ID]],'Customer_Dim'!A:A,'Customer_Dim'!K:K,"Not Found") -> Gold | P3: =_xlfn.XLOOKUP(Sales_fact[[#This Row],[Customer_ID]],'Customer_Dim'!A:A, 'Customer_Dim'!E:E, "Not Found") -> 63 | Q3: =VLOOKUP(Sales_fact[[#This Row],[Customer_ID]], 'Customer_Dim'!A:F, 6, FALSE) -> Female | R3: =_xlfn.XLOOKUP(Sales_fact[[#This Row],[Product_ID]],Product_Dim!A:A,Product_Dim!C:C,"OTHERS") -> Electronics
A4: SALE2 | B4: 45446 | C4: CUST1056 | D4: PROD49 | E4: =TRIM(Sales_fact[[#This Row],[Store_ID]]) -> STORE8 | F4: 4 | G4: =IF(ISBLANK(F4),MODE($F$2:$F$2001),F4) -> 4 | H4: 914.05 | I4: =IF(ISBLANK(H4),AVERAGE($H$2:$H$2001),H4) -> 914.05 | J4: 0.25 | K4: =IF(ISBLANK(J4),MODE($J$2:$J$2001),J4) -> 0.25 | L4: Credit Card | M4: 2742.15 | N4: =G4*I4*(1-K4) -> 2742.15 | O4: =_xlfn.XLOOKUP(Sales_fact[[#This Row],[Customer_ID]],'Customer_Dim'!A:A,'Customer_Dim'!K:K,"Not Found") -> Gold | P4: =_xlfn.XLOOKUP(Sales_fact[[#This Row],[Customer_ID]],'Customer_Dim'!A:A, 'Customer_Dim'!E:E, "Not Found") -> 49 | Q4: =VLOOKUP(Sales_fact[[#This Row],[Customer_ID]], 'Customer_Dim'!A:F, 6, FALSE) -> Female | R4: =_xlfn.XLOOKUP(Sales_fact[[#This Row],[Product_ID]],Product_Dim!A:A,Product_Dim!C:C,"OTHERS") -> Beauty | T4: Mean | U4: 1086.6817
A5: SALE3 | B5: 45259 | C5: CUST1346 | D5: PROD76 | E5: =TRIM(Sales_fact[[#This Row],[Store_ID]]) -> STORE8 | F5: 1 | G5: =IF(ISBLANK(F5),MODE($F$2:$F$2001),F5) -> 1 | H5: 921.51 | I5: =IF(ISBLANK(H5),AVERAGE($H$2:$H$2001),H5) -> 921.51 | J5: 0.16 | K5: =IF(ISBLANK(J5),MODE($J$2:$J$2001),J5) -> 0.16 | L5: COD | M5: 774.0684 | N5: =G5*I5*(1-K5) -> 774.0684 | O5: =_xlfn.XLOOKUP(Sales_fact[[#This Row],[Customer_ID]],'Customer_Dim'!A:A,'Customer_Dim'!K:K,"Not Found") -> Platinum | P5: =_xlfn.XLOOKUP(Sales_fact[[#This Row],[Customer_ID]],'Customer_Dim'!A:A, 'Customer_Dim'!E:E, "Not Found") -> 58 | Q5: =VLOOKUP(Sales_fact[[#This Row],[Customer_ID]], 'Customer_Dim'!A:F, 6, FALSE) -> Female | R5: =_xlfn.XLOOKUP(Sales_fact[[#This Row],[Product_ID]],Product_Dim!A:A,Product_Dim!C:C,"OTHERS") -> Electronics | T5: Standard Error | U5: 18.303306
A6: SALE4 | B6: 45297 | C6: CUST1493 | D6: PROD59 | E6: =TRIM(Sales_fact[[#This Row],[Store_ID]]) -> STORE5 | F6: 3 | G6: =IF(ISBLANK(F6),MODE($F$2:$F$2001),F6) -> 3 | H6: 745.3 | I6: =IF(ISBLANK(H6),AVERAGE($H$2:$H$2001),H6) -> 745.3 | J6: 0.18 | K6: =IF(ISBLANK(J6),MODE($J$2:$J$2001),J6) -> 0.18 | L6: Credit Card | M6: 1833.438 | N6: =G6*I6*(1-K6) -> 1833.438 | O6: =_xlfn.XLOOKUP(Sales_fact[[#This Row],[Customer_ID]],'Customer_Dim'!A:A,'Customer_Dim'!K:K,"Not Found") -> Silver | P6: =_xlfn.XLOOKUP(Sales_fact[[#This Row],[Customer_ID]],'Customer_Dim'!A:A, 'Customer_Dim'!E:E, "Not Found") -> 28 | Q6: =VLOOKUP(Sales_fact[[#This Row],[Customer_ID]], 'Customer_Dim'!A:F, 6, FALSE) -> Male | R6: =_xlfn.XLOOKUP(Sales_fact[[#This Row],[Product_ID]],Product_Dim!A:A,Product_Dim!C:C,"OTHERS") -> Beauty | T6: Median | U6: 868.7182
A7: SALE5 | B7: 45499 | C7: CUST1116 | D7: PROD15 | E7: =TRIM(Sales_fact[[#This Row],[Store_ID]]) -> STORE7 | F7: 3 | G7: =IF(ISBLANK(F7),MODE($F$2:$F$2001),F7) -> 3 | H7: 147.01 | I7: =IF(ISBLANK(H7),AVERAGE($H$2:$H$2001),H7) -> 147.01 | J7: 0.19 | K7: =IF(ISBLANK(J7),MODE($J$2:$J$2001),J7) -> 0.19 | L7: COD | M7: 357.2343 | N7: =G7*I7*(1-K7) -> 357.2343 | O7: =_xlfn.XLOOKUP(Sales_fact[[#This Row],[Customer_ID]],'Customer_Dim'!A:A,'Customer_Dim'!K:K,"Not Found") -> Platinum | P7: =_xlfn.XLOOKUP(Sales_fact[[#This Row],[Customer_ID]],'Customer_Dim'!A:A, 'Customer_Dim'!E:E, "Not Found") -> 18 | Q7: =VLOOKUP(Sales_fact[[#This Row],[Customer_ID]], 'Customer_Dim'!A:F, 6, FALSE) -> Female | R7: =_xlfn.XLOOKUP(Sales_fact[[#This Row],[Product_ID]],Product_Dim!A:A,Product_Dim!C:C,"OTHERS") -> Electronics | T7: Mode | U7: #N/A
A8: SALE6 | B8: 45850 | C8: CUST1016 | D8: PROD56 | E8: =TRIM(Sales_fact[[#This Row],[Store_ID]]) -> STORE4 | F8: 2 | G8: =IF(ISBLANK(F8),MODE($F$2:$F$2001),F8) -> 2 | H8: 785.31 | I8: =IF(ISBLANK(H8),AVERAGE($H$2:$H$2001),H8) -> 785.31 | J8: 0.15 | K8: =IF(ISBLANK(J8),MODE($J$2:$J$2001),J8) -> 0.15 | L8: PayPal | M8: 1335.027 | N8: =G8*I8*(1-K8) -> 1335.027 | O8: =_xlfn.XLOOKUP(Sales_fact[[#This Row],[Customer_ID]],'Customer_Dim'!A:A,'Customer_Dim'!K:K,"Not Found") -> Bronze | P8: =_xlfn.XLOOKUP(Sales_fact[[#This Row],[Customer_ID]],'Customer_Dim'!A:A, 'Customer_Dim'!E:E, "Not Found") -> 24 | Q8: =VLOOKUP(Sales_fact[[#This Row],[Customer_ID]], 'Customer_Dim'!A:F, 6, FALSE) -> Female | R8: =_xlfn.XLOOKUP(Sales_fact[[#This Row],[Product_ID]],Product_Dim!A:A,Product_Dim!C:C,"OTHERS") -> Home | T8: Standard Deviation | U8: 818.54871
A9: SALE7 | B9: 45248 | C9: CUST1152 | D9: PROD70 | E9: =TRIM(Sales_fact[[#This Row],[Store_ID]]) -> STORE8 | F9: 4 | G9: =IF(ISBLANK(F9),MODE($F$2:$F$2001),F9) -> 4 | H9: 342.39 | I9: =IF(ISBLANK(H9),AVERAGE($H$2:$H$2001),H9) -> 342.39 | J9: 0.23 | K9: =IF(ISBLANK(J9),MODE($J$2:$J$2001),J9) -> 0.23 | L9: PayPal | M9: 1054.5612 | N9: =G9*I9*(1-K9) -> 1054.5612 | O9: =_xlfn.XLOOKUP(Sales_fact[[#This Row],[Customer_ID]],'Customer_Dim'!A:A,'Customer_Dim'!K:K,"Not Found") -> Platinum | P9: =_xlfn.XLOOKUP(Sales_fact[[#This Row],[Customer_ID]],'Customer_Dim'!A:A, 'Customer_Dim'!E:E, "Not Found") -> 41 | Q9: =VLOOKUP(Sales_fact[[#This Row],[Customer_ID]], 'Customer_Dim'!A:F, 6, FALSE) -> Female | R9: =_xlfn.XLOOKUP(Sales_fact[[#This Row],[Product_ID]],Product_Dim!A:A,Product_Dim!C:C,"OTHERS") -> Home | T9: Sample Variance | U9: 670021.99
A10: SALE8 | B10: 45781 | C10: CUST1187 | D10: PROD99 | E10: =TRIM(Sales_fact[[#This Row],[Store_ID]]) -> STORE5 | G10: =IF(ISBLANK(F10),MODE($F$2:$F$2001),F10) -> 2 | H10: 448.25 | I10: =IF(ISBLANK(H10),AVERAGE($H$2:$H$2001),H10) -> 448.25 | J10: 0.07 | K10: =IF(ISBLANK(J10),MODE($J$2:$J$2001),J10) -> 0.07 | L10: PayPal | M10: 1250.6175 | N10: =G10*I10*(1-K10) -> 833.745 | O10: =_xlfn.XLOOKUP(Sales_fact[[#This Row],[Customer_ID]],'Customer_Dim'!A:A,'Customer_Dim'!K:K,"Not Found") -> Platinum | P10: =_xlfn.XLOOKUP(Sales_fact[[#This Row],[Customer_ID]],'Customer_Dim'!A:A, 'Customer_Dim'!E:E, "Not Found") -> 60 | Q10: =VLOOKUP(Sales_fact[[#This Row],[Customer_ID]], 'Customer_Dim'!A:F, 6, FALSE) -> Female | R10: =_xlfn.XLOOKUP(Sales_fact[[#This Row],[Product_ID]],Product_Dim!A:A,Product_Dim!C:C,"OTHERS") -> Home | T10: Kurtosis | U10: 0.059022757
A11: SALE9 | B11: 45869 | C11: CUST1464 | D11: PROD33 | E11: =TRIM(Sales_fact[[#This Row],[Store_ID]]) -> STORE0 | F11: 2 | G11: =IF(ISBLANK(F11),MODE($F$2:$F$2001),F11) -> 2 | H11: 873.17 | I11: =IF(ISBLANK(H11),AVERAGE($H$2:$H$2001),H11) -> 873.17 | J11: 0.23 | K11: =IF(ISBLANK(J11),MODE($J$2:$J$2001),J11) -> 0.23 | L11: PayPal | M11: 1344.6818 | N11: =G11*I11*(1-K11) -> 1344.6818 | O11: =_xlfn.XLOOKUP(Sales_fact[[#This Row],[Customer_ID]],'Customer_Dim'!A:A,'Customer_Dim'!K:K,"Not Found") -> Not Found | P11: =_xlfn.XLOOKUP(Sales_fact[[#This Row],[Customer_ID]],'Customer_Dim'!A:A, 'Customer_Dim'!E:E, "Not Found") -> Not Found | Q11: =VLOOKUP(Sales_fact[[#This Row],[Customer_ID]], 'Customer_Dim'!A:F, 6, ) -> #N/A | R11: =_xlfn.XLOOKUP(Sales_fact[[#This Row],[Product_ID]],Product_Dim!A:A,Product_Dim!C:C,"OTHERS") -> Home | T11: Skewness | U11: 0.8819083
A12: SALE10 | B12: 45335 | C12: CUST1065 | D12: PROD24 | E12: =TRIM(Sales_fact[[#This Row],[Store_ID]]) -> STORE14 | F12: 1 | G12: =IF(ISBLANK(F12),MODE($F$2:$F$2001),F12) -> 1 | H12: 278.63 | I12: =IF(ISBLANK(H12),AVERAGE($H$2:$H$2001),H12) -> 278.63 | J12: 0.07 | K12: =IF(ISBLANK(J12),MODE($J$2:$J$2001),J12) -> 0.07 | L12: Credit Card | M12: 259.1259 | N12: =G12*I12*(1-K12) -> 259.1259 | O12: =_xlfn.XLOOKUP(Sales_fact[[#This Row],[Customer_ID]],'Customer_Dim'!A:A,'Customer_Dim'!K:K,"Not Found") -> Silver | P12: =_xlfn.XLOOKUP(Sales_fact[[#This Row],[Customer_ID]],'Customer_Dim'!A:A, 'Customer_Dim'!E:E, "Not Found") -> 21 | Q12: =VLOOKUP(Sales_fact[[#This Row],[Customer_ID]], 'Customer_Dim'!A:F, 6, FALSE) -> Female | R12: =_xlfn.XLOOKUP(Sales_fact[[#This Row],[Product_ID]],Product_Dim!A:A,Product_Dim!C:C,"OTHERS") -> Sports | T12: Range | U12: 3889.7838
A13: SALE11 | B13: 45801 | C13: CUST1320 | D13: PROD39 | E13: =TRIM(Sales_fact[[#This Row],[Store_ID]]) -> STORE1 | F13: 4 | G13: =IF(ISBLANK(F13),MODE($F$2:$F$2001),F13) -> 4 | H13: 286.92 | I13: =IF(ISBLANK(H13),AVERAGE($H$2:$H$2001),H13) -> 286.92 | J13: 0.17 | K13: =IF(ISBLANK(J13),MODE($J$2:$J$2001),J13) -> 0.17 | L13: Credit Card | M13: 952.5744 | N13: =G13*I13*(1-K13) -> 952.5744 | O13: =_xlfn.XLOOKUP(Sales_fact[[#This Row],[Customer_ID]],'Customer_Dim'!A:A,'Customer_Dim'!K:K,"Not Found") -> Bronze | P13: =_xlfn.XLOOKUP(Sales_fact[[#This Row],[Customer_ID]],'Customer_Dim'!A:A, 'Customer_Dim'!E:E, "Not Found") -> 34 | Q13: =VLOOKUP(Sales_fact[[#This Row],[Customer_ID]], 'Customer_Dim'!A:F, 6, FALSE) -> Female | R13: =_xlfn.XLOOKUP(Sales_fact[[#This Row],[Product_ID]],Product_Dim!A:A,Product_Dim!C:C,"OTHERS") -> Electronics | T13: Minimum | U13: 18.459
A14: SALE12 | B14: 45528 | C14: CUST1237 | D14: PROD88 | E14: =TRIM(Sales_fact[[#This Row],[Store_ID]]) -> STORE4 | F14: 4 | G14: =IF(ISBLANK(F14),MODE($F$2:$F$2001),F14) -> 4 | H14: 644.58 | I14: =IF(ISBLANK(H14),AVERAGE($H$2:$H$2001),H14) -> 644.58 | J14: 0.01 | K14: =IF(ISBLANK(J14),MODE($J$2:$J$2001),J14) -> 0.01 | L14: Credit Card | M14: 2552.5368 | N14: =G14*I14*(1-K14) -> 2552.5368 | O14: =_xlfn.XLOOKUP(Sales_fact[[#This Row],[Customer_ID]],'Customer_Dim'!A:A,'Customer_Dim'!K:K,"Not Found") -> Gold | P14: =_xlfn.XLOOKUP(Sales_fact[[#This Row],[Customer_ID]],'Customer_Dim'!A:A, 'Customer_Dim'!E:E, "Not Found") -> 41 | Q14: =VLOOKUP(Sales_fact[[#This Row],[Customer_ID]], 'Customer_Dim'!A:F, 6, FALSE) -> Female | R14: =_xlfn.XLOOKUP(Sales_fact[[#This Row],[Product_ID]],Product_Dim!A:A,Product_Dim!C:C,"OTHERS") -> Sports | T14: Maximum | U14: 3908.2428
A15: SALE13 | B15: 45875 | C15: CUST1443 | D15: PROD34 | E15: =TRIM(Sales_fact[[#This Row],[Store_ID]]) -> STORE16 | F15: 2 | G15: =IF(ISBLANK(F15),MODE($F$2:$F$2001),F15) -> 2 | H15: 316.9 | I15: =IF(ISBLANK(H15),AVERAGE($H$2:$H$2001),H15) -> 316.9 | J15: 0.3 | K15: =IF(ISBLANK(J15),MODE($J$2:$J$2001),J15) -> 0.3 | L15: PayPal | M15: 443.66 | N15: =G15*I15*(1-K15) -> 443.66 | O15: =_xlfn.XLOOKUP(Sales_fact[[#This Row],[Customer_ID]],'Customer_Dim'!A:A,'Customer_Dim'!K:K,"Not Found") -> Silver | P15: =_xlfn.XLOOKUP(Sales_fact[[#This Row],[Customer_ID]],'Customer_Dim'!A:A, 'Customer_Dim'!E:E, "Not Found") -> 51 | Q15: =VLOOKUP(Sales_fact[[#This Row],[Customer_ID]], 'Customer_Dim'!A:F, 6, FALSE) -> Male | R15: =_xlfn.XLOOKUP(Sales_fact[[#This Row],[Product_ID]],Product_Dim!A:A,Product_Dim!C:C,"OTHERS") -> Electronics | T15: Sum | U15: 2173363.4
A16: SALE14 | B16: 45829 | C16: CUST1348 | D16: PROD24 | E16: =TRIM(Sales_fact[[#This Row],[Store_ID]]) -> STORE15 | F16: 4 | G16: =IF(ISBLANK(F16),MODE($F$2:$F$2001),F16) -> 4 | H16: 403.47 | I16: =IF(ISBLANK(H16),AVERAGE($H$2:$H$2001),H16) -> 403.47 | J16: 0.29 | K16: =IF(ISBLANK(J16),MODE($J$2:$J$2001),J16) -> 0.29 | L16: PayPal | M16: 1145.8548 | N16: =G16*I16*(1-K16) -> 1145.8548 | O16: =_xlfn.XLOOKUP(Sales_fact[[#This Row],[Customer_ID]],'Customer_Dim'!A:A,'Customer_Dim'!K:K,"Not Found") -> Silver | P16: =_xlfn.XLOOKUP(Sales_fact[[#This Row],[Customer_ID]],'Customer_Dim'!A:A, 'Customer_Dim'!E:E, "Not Found") -> 55 | Q16: =VLOOKUP(Sales_fact[[#This Row],[Customer_ID]], 'Customer_Dim'!A:F, 6, FALSE) -> Male | R16: =_xlfn.XLOOKUP(Sales_fact[[#This Row],[Product_ID]],Product_Dim!A:A,Product_Dim!C:C,"OTHERS") -> Sports | T16: Count | U16: 2000
A17: SALE15 | B17: 45636 | C17: CUST1435 | D17: PROD36 | E17: =TRIM(Sales_fact[[#This Row],[Store_ID]]) -> STORE9 | G17: =IF(ISBLANK(F17),MODE($F$2:$F$2001),F17) -> 2 | H17: 871.34 | I17: =IF(ISBLANK(H17),AVERAGE($H$2:$H$2001),H17) -> 871.34 | J17: 0.04 | K17: =IF(ISBLANK(J17),MODE($J$2:$J$2001),J17) -> 0.04 | L17: COD | M17: 2509.4592 | N17: =G17*I17*(1-K17) -> 1672.9728 | O17: =_xlfn.XLOOKUP(Sales_fact[[#This Row],[Customer_ID]],'Customer_Dim'!A:A,'Customer_Dim'!K:K,"Not Found") -> Silver | P17: =_xlfn.XLOOKUP(Sales_fact[[#This Row],[Customer_ID]],'Customer_Dim'!A:A, 'Customer_Dim'!E:E, "Not Found") -> 37 | Q17: =VLOOKUP(Sales_fact[[#This Row],[Customer_ID]], 'Customer_Dim'!A:F, 6, FALSE) -> Female | R17: =_xlfn.XLOOKUP(Sales_fact[[#This Row],[Product_ID]],Product_Dim!A:A,Product_Dim!C:C,"OTHERS") -> Clothing
A18: SALE16 | B18: 45913 | C18: CUST1276 | D18: PROD65 | E18: =TRIM(Sales_fact[[#This Row],[Store_ID]]) -> STORE19 | F18: 2 | G18: =IF(ISBLANK(F18),MODE($F$2:$F$2001),F18) -> 2 | H18: 451.98 | I18: =IF(ISBLANK(H18),AVERAGE($H$2:$H$2001),H18) -> 451.98 | J18: 0.25 | K18: =IF(ISBLANK(J18),MODE($J$2:$J$2001),J18) -> 0.25 | L18: Credit Card | M18: 677.97 | N18: =G18*I18*(1-K18) -> 677.97 | O18: =_xlfn.XLOOKUP(Sales_fact[[#This Row],[Customer_ID]],'Customer_Dim'!A:A,'Customer_Dim'!K:K,"Not Found") -> Gold | P18: =_xlfn.XLOOKUP(Sales_fact[[#This Row],[Customer_ID]],'Customer_Dim'!A:A, 'Customer_Dim'!E:E, "Not Found") -> 38 | Q18: =VLOOKUP(Sales_fact[[#This Row],[Customer_ID]], 'Customer_Dim'!A:F, 6, FALSE) -> Male | R18: =_xlfn.XLOOKUP(Sales_fact[[#This Row],[Product_ID]],Product_Dim!A:A,Product_Dim!C:C,"OTHERS") -> Sports
A19: SALE17 | B19: 45637 | C19: CUST1079 | D19: PROD27 | E19: =TRIM(Sales_fact[[#This Row],[Store_ID]]) -> STORE4 | F19: 2 | G19: =IF(ISBLANK(F19),MODE($F$2:$F$2001),F19) -> 2 | H19: 502.69 | I19: =IF(ISBLANK(H19),AVERAGE($H$2:$H$2001),H19) -> 502.69 | J19: 0.23 | K19: =IF(ISBLANK(J19),MODE($J$2:$J$2001),J19) -> 0.23 | L19: Credit Card | M19: 774.1426 | N19: =G19*I19*(1-K19) -> 774.1426 | O19: =_xlfn.XLOOKUP(Sales_fact[[#This Row],[Customer_ID]],'Customer_Dim'!A:A,'Customer_Dim'!K:K,"Not Found") -> Platinum | P19: =_xlfn.XLOOKUP(Sales_fact[[#This Row],[Customer_ID]],'Customer_Dim'!A:A, 'Customer_Dim'!E:E, "Not Found") -> 22 | Q19: =VLOOKUP(Sales_fact[[#This Row],[Customer_ID]], 'Customer_Dim'!A:F, 6, FALSE) -> Female | R19: =_xlfn.XLOOKUP(Sales_fact[[#This Row],[Product_ID]],Product_Dim!A:A,Product_Dim!C:C,"OTHERS") -> Home
A20: SALE18 | B20: 45517 | C20: CUST1094 | D20: PROD39 | E20: =TRIM(Sales_fact[[#This Row],[Store_ID]]) -> STORE4 | F20: 2 | G20: =IF(ISBLANK(F20),MODE($F$2:$F$2001),F20) -> 2 | H20: 559.23 | I20: =IF(ISBLANK(H20),AVERAGE($H$2:$H$2001),H20) -> 559.23 | J20: 0.25 | K20: =IF(ISBLANK(J20),MODE($J$2:$J$2001),J20) -> 0.25 | L20: COD | M20: 838.845 | N20: =G20*I20*(1-K20) -> 838.845 | O20: =_xlfn.XLOOKUP(Sales_fact[[#This Row],[Customer_ID]],'Customer_Dim'!A:A,'Customer_Dim'!K:K,"Not Found") -> Gold | P20: =_xlfn.XLOOKUP(Sales_fact[[#This Row],[Customer_ID]],'Customer_Dim'!A:A, 'Customer_Dim'!E:E, "Not Found") -> 43 | Q20: =VLOOKUP(Sales_fact[[#This Row],[Customer_ID]], 'Customer_Dim'!A:F, 6, FALSE) -> Female | R20: =_xlfn.XLOOKUP(Sales_fact[[#This Row],[Product_ID]],Product_Dim!A:A,Product_Dim!C:C,"OTHERS") -> Electronics
A21: SALE19 | B21: 45369 | C21: CUST1239 | D21: PROD60 | E21: =TRIM(Sales_fact[[#This Row],[Store_ID]]) -> STORE13 | F21: 4 | G21: =IF(ISBLANK(F21),MODE($F$2:$F$2001),F21) -> 4 | I21: =IF(ISBLANK(H21),AVERAGE($H$2:$H$2001),H21) -> 513.98477 | J21: 0.04 | K21: =IF(ISBLANK(J21),MODE($J$2:$J$2001),J21) -> 0.04 | L21: COD | M21: 1782.4512 | N21: =G21*I21*(1-K21) -> 1973.7015 | O21: =_xlfn.XLOOKUP(Sales_fact[[#This Row],[Customer_ID]],'Customer_Dim'!A:A,'Customer_Dim'!K:K,"Not Found") -> Platinum | P21: =_xlfn.XLOOKUP(Sales_fact[[#This Row],[Customer_ID]],'Customer_Dim'!A:A, 'Customer_Dim'!E:E, "Not Found") -> 58 | Q21: =VLOOKUP(Sales_fact[[#This Row],[Customer_ID]], 'Customer_Dim'!A:F, 6, FALSE) -> Female | R21: =_xlfn.XLOOKUP(Sales_fact[[#This Row],[Product_ID]],Product_Dim!A:A,Product_Dim!C:C,"OTHERS") -> Beauty
A22: SALE20 | B22: 45843 | C22: CUST1144 | D22: PROD72 | E22: =TRIM(Sales_fact[[#This Row],[Store_ID]]) -> STORE17 | F22: 3 | G22: =IF(ISBLANK(F22),MODE($F$2:$F$2001),F22) -> 3 | H22: 986.04 | I22: =IF(ISBLANK(H22),AVERAGE($H$2:$H$2001),H22) -> 986.04 | J22: 0.27 | K22: =IF(ISBLANK(J22),MODE($J$2:$J$2001),J22) -> 0.27 | L22: COD | M22: 2159.4276 | N22: =G22*I22*(1-K22) -> 2159.4276 | O22: =_xlfn.XLOOKUP(Sales_fact[[#This Row],[Customer_ID]],'Customer_Dim'!A:A,'Customer_Dim'!K:K,"Not Found") -> Bronze | P22: =_xlfn.XLOOKUP(Sales_fact[[#This Row],[Customer_ID]],'Customer_Dim'!A:A, 'Customer_Dim'!E:E, "Not Found") -> 62 | Q22: =VLOOKUP(Sales_fact[[#This Row],[Customer_ID]], 'Customer_Dim'!A:F, 6, FALSE) -> Female | R22: =_xlfn.XLOOKUP(Sales_fact[[#This Row],[Product_ID]],Product_Dim!A:A,Product_Dim!C:C,"OTHERS") -> Sports
A23: SALE21 | B23: 45447 | C23: CUST1396 | D23: PROD43 | E23: =TRIM(Sales_fact[[#This Row],[Store_ID]]) -> STORE18 | F23: 1 | G23: =IF(ISBLANK(F23),MODE($F$2:$F$2001),F23) -> 1 | H23: 589.56 | I23: =IF(ISBLANK(H23),AVERAGE($H$2:$H$2001),H23) -> 589.56 | J23: 0.22 | K23: =IF(ISBLANK(J23),MODE($J$2:$J$2001),J23) -> 0.22 | L23: Credit Card | M23: 459.8568 | N23: =G23*I23*(1-K23) -> 459.8568 | O23: =_xlfn.XLOOKUP(Sales_fact[[#This Row],[Customer_ID]],'Customer_Dim'!A:A,'Customer_Dim'!K:K,"Not Found") -> Silver | P23: =_xlfn.XLOOKUP(Sales_fact[[#This Row],[Customer_ID]],'Customer_Dim'!A:A, 'Customer_Dim'!E:E, "Not Found") -> 25 | Q23: =VLOOKUP(Sales_fact[[#This Row],[Customer_ID]], 'Customer_Dim'!A:F, 6, FALSE) -> Female | R23: =_xlfn.XLOOKUP(Sales_fact[[#This Row],[Product_ID]],Product_Dim!A:A,Product_Dim!C:C,"OTHERS") -> Electronics
A24: SALE22 | B24: 45394 | C24: CUST1476 | D24: PROD69 | E24: =TRIM(Sales_fact[[#This Row],[Store_ID]]) -> STORE10 | F24: 3 | G24: =IF(ISBLANK(F24),MODE($F$2:$F$2001),F24) -> 3 | H24: 979.42 | I24: =IF(ISBLANK(H24),AVERAGE($H$2:$H$2001),H24) -> 979.42 | J24: 0.03 | K24: =IF(ISBLANK(J24),MODE($J$2:$J$2001),J24) -> 0.03 | L24: PayPal | M24: 2850.1122 | N24: =G24*I24*(1-K24) -> 2850.1122 | O24: =_xlfn.XLOOKUP(Sales_fact[[#This Row],[Customer_ID]],'Customer_Dim'!A:A,'Customer_Dim'!K:K,"Not Found") -> Gold | P24: =_xlfn.XLOOKUP(Sales_fact[[#This Row],[Customer_ID]],'Customer_Dim'!A:A, 'Customer_Dim'!E:E, "Not Found") -> 33 | Q24: =VLOOKUP(Sales_fact[[#This Row],[Customer_ID]], 'Customer_Dim'!A:F, 6, FALSE) -> Female | R24: =_xlfn.XLOOKUP(Sales_fact[[#This Row],[Product_ID]],Product_Dim!A:A,Product_Dim!C:C,"OTHERS") -> Clothing
A25: SALE23 | B25: 45466 | C25: CUST1368 | D25: PROD12 | E25: =TRIM(Sales_fact[[#This Row],[Store_ID]]) -> STORE8 | F25: 1 | G25: =IF(ISBLANK(F25),MODE($F$2:$F$2001),F25) -> 1 | H25: 719.28 | I25: =IF(ISBLANK(H25),AVERAGE($H$2:$H$2001),H25) -> 719.28 | J25: 0.08 | K25: =IF(ISBLANK(J25),MODE($J$2:$J$2001),J25) -> 0.08 | L25: Credit Card | M25: 661.7376 | N25: =G25*I25*(1-K25) -> 661.7376 | O25: =_xlfn.XLOOKUP(Sales_fact[[#This Row],[Customer_ID]],'Customer_Dim'!A:A,'Customer_Dim'!K:K,"Not Found") -> Platinum | P25: =_xlfn.XLOOKUP(Sales_fact[[#This Row],[Customer_ID]],'Customer_Dim'!A:A, 'Customer_Dim'!E:E, "Not Found") -> 34 | Q25: =VLOOKUP(Sales_fact[[#This Row],[Customer_ID]], 'Customer_Dim'!A:F, 6, FALSE) -> Female | R25: =_xlfn.XLOOKUP(Sales_fact[[#This Row],[Product_ID]],Product_Dim!A:A,Product_Dim!C:C,"OTHERS") -> Beauty
A26: SALE24 | B26: 45908 | C26: CUST1186 | D26: PROD67 | E26: =TRIM(Sales_fact[[#This Row],[Store_ID]]) -> STORE6 | F26: 3 | G26: =IF(ISBLANK(F26),MODE($F$2:$F$2001),F26) -> 3 | H26: 77.6 | I26: =IF(ISBLANK(H26),AVERAGE($H$2:$H$2001),H26) -> 77.6 | J26: 0.07 | K26: =IF(ISBLANK(J26),MODE($J$2:$J$2001),J26) -> 0.07 | L26: Credit Card | M26: 216.504 | N26: =G26*I26*(1-K26) -> 216.504 | O26: =_xlfn.XLOOKUP(Sales_fact[[#This Row],[Customer_ID]],'Customer_Dim'!A:A,'Customer_Dim'!K:K,"Not Found") -> Silver | P26: =_xlfn.XLOOKUP(Sales_fact[[#This Row],[Customer_ID]],'Customer_Dim'!A:A, 'Customer_Dim'!E:E, "Not Found") -> 53 | Q26: =VLOOKUP(Sales_fact[[#This Row],[Customer_ID]], 'Customer_Dim'!A:F, 6, FALSE) -> Male | R26: =_xlfn.XLOOKUP(Sales_fact[[#This Row],[Product_ID]],Product_Dim!A:A,Product_Dim!C:C,"OTHERS") -> Electronics
A27: SALE25 | B27: 45552 | C27: CUST1381 | D27: PROD5 | E27: =TRIM(Sales_fact[[#This Row],[Store_ID]]) -> STORE3 | F27: 4 | G27: =IF(ISBLANK(F27),MODE($F$2:$F$2001),F27) -> 4 | H27: 852.71 | I27: =IF(ISBLANK(H27),AVERAGE($H$2:$H$2001),H27) -> 852.71 | J27: 0.14 | K27: =IF(ISBLANK(J27),MODE($J$2:$J$2001),J27) -> 0.14 | L27: PayPal | M27: 2933.3224 | N27: =G27*I27*(1-K27) -> 2933.3224 | O27: =_xlfn.XLOOKUP(Sales_fact[[#This Row],[Customer_ID]],'Customer_Dim'!A:A,'Customer_Dim'!K:K,"Not Found") -> Silver | P27: =_xlfn.XLOOKUP(Sales_fact[[#This Row],[Customer_ID]],'Customer_Dim'!A:A, 'Customer_Dim'!E:E, "Not Found") -> 50 | Q27: =VLOOKUP(Sales_fact[[#This Row],[Customer_ID]], 'Customer_Dim'!A:F, 6, FALSE) -> Male | R27: =_xlfn.XLOOKUP(Sales_fact[[#This Row],[Product_ID]],Product_Dim!A:A,Product_Dim!C:C,"OTHERS") -> Clothing
A28: SALE26 | B28: 45294 | C28: CUST1213 | D28: PROD98 | E28: =TRIM(Sales_fact[[#This Row],[Store_ID]]) -> STORE8 | F28: 4 | G28: =IF(ISBLANK(F28),MODE($F$2:$F$2001),F28) -> 4 | H28: 156.16 | I28: =IF(ISBLANK(H28),AVERAGE($H$2:$H$2001),H28) -> 156.16 | K28: =IF(ISBLANK(J28),MODE($J$2:$J$2001),J28) -> 0.1 | L28: Credit Card | M28: 599.6544 | N28: =G28*I28*(1-K28) -> 562.176 | O28: =_xlfn.XLOOKUP(Sales_fact[[#This Row],[Customer_ID]],'Customer_Dim'!A:A,'Customer_Dim'!K:K,"Not Found") -> Platinum | P28: =_xlfn.XLOOKUP(Sales_fact[[#This Row],[Customer_ID]],'Customer_Dim'!A:A, 'Customer_Dim'!E:E, "Not Found") -> 42 | Q28: =VLOOKUP(Sales_fact[[#This Row],[Customer_ID]], 'Customer_Dim'!A:F, 6, FALSE) -> Female | R28: =_xlfn.XLOOKUP(Sales_fact[[#This Row],[Product_ID]],Product_Dim!A:A,Product_Dim!C:C,"OTHERS") -> Electronics
A29: SALE27 | B29: 45710 | C29: CUST1200 | D29: PROD77 | E29: =TRIM(Sales_fact[[#This Row],[Store_ID]]) -> STORE8 | F29: 3 | G29: =IF(ISBLANK(F29),MODE($F$2:$F$2001),F29) -> 3 | H29: 815.49 | I29: =IF(ISBLANK(H29),AVERAGE($H$2:$H$2001),H29) -> 815.49 | J29: 0.17 | K29: =IF(ISBLANK(J29),MODE($J$2:$J$2001),J29) -> 0.17 | L29: Credit Card | M29: 2030.5701 | N29: =G29*I29*(1-K29) -> 2030.5701 | O29: =_xlfn.XLOOKUP(Sales_fact[[#This Row],[Customer_ID]],'Customer_Dim'!A:A,'Customer_Dim'!K:K,"Not Found") -> Platinum | P29: =_xlfn.XLOOKUP(Sales_fact[[#This Row],[Customer_ID]],'Customer_Dim'!A:A, 'Customer_Dim'!E:E, "Not Found") -> 30 | Q29: =VLOOKUP(Sales_fact[[#This Row],[Customer_ID]], 'Customer_Dim'!A:F, 6, FALSE) -> Male | R29: =_xlfn.XLOOKUP(Sales_fact[[#This Row],[Product_ID]],Product_Dim!A:A,Product_Dim!C:C,"OTHERS") -> Electronics
A30: SALE28 | B30: 45923 | C30: CUST1148 | D30: PROD13 | E30: =TRIM(Sales_fact[[#This Row],[Store_ID]]) -> STORE2 | F30: 2 | G30: =IF(ISBLANK(F30),MODE($F$2:$F$2001),F30) -> 2 | H30: 74.21 | I30: =IF(ISBLANK(H30),AVERAGE($H$2:$H$2001),H30) -> 74.21 | J30: 0.11 | K30: =IF(ISBLANK(J30),MODE($J$2:$J$2001),J30) -> 0.11 | L30: PayPal | M30: 132.0938 | N30: =G30*I30*(1-K30) -> 132.0938 | O30: =_xlfn.XLOOKUP(Sales_fact[[#This Row],[Customer_ID]],'Customer_Dim'!A:A,'Customer_Dim'!K:K,"Not Found") -> Bronze | P30: =_xlfn.XLOOKUP(Sales_fact[[#This Row],[Customer_ID]],'Customer_Dim'!A:A, 'Customer_Dim'!E:E, "Not Found") -> 42 | Q30: =VLOOKUP(Sales_fact[[#This Row],[Customer_ID]], 'Customer_Dim'!A:F, 6, FALSE) -> Female | R30: =_xlfn.XLOOKUP(Sales_fact[[#This Row],[Product_ID]],Product_Dim!A:A,Product_Dim!C:C,"OTHERS") -> Electronics
A31: SALE29 | B31: 45302 | C31: CUST1348 | D31: PROD99 | E31: =TRIM(Sales_fact[[#This Row],[Store_ID]]) -> STORE3 | G31: =IF(ISBLANK(F31),MODE($F$2:$F$2001),F31) -> 2 | H31: 451.67 | I31: =IF(ISBLANK(H31),AVERAGE($H$2:$H$2001),H31) -> 451.67 | J31: 0.15 | K31: =IF(ISBLANK(J31),MODE($J$2:$J$2001),J31) -> 0.15 | L31: Credit Card | M31: 1535.678 | N31: =G31*I31*(1-K31) -> 767.839 | O31: =_xlfn.XLOOKUP(Sales_fact[[#This Row],[Customer_ID]],'Customer_Dim'!A:A,'Customer_Dim'!K:K,"Not Found") -> Silver | P31: =_xlfn.XLOOKUP(Sales_fact[[#This Row],[Customer_ID]],'Customer_Dim'!A:A, 'Customer_Dim'!E:E, "Not Found") -> 55 | Q31: =VLOOKUP(Sales_fact[[#This Row],[Customer_ID]], 'Customer_Dim'!A:F, 6, FALSE) -> Male | R31: =_xlfn.XLOOKUP(Sales_fact[[#This Row],[Product_ID]],Product_Dim!A:A,Product_Dim!C:C,"OTHERS") -> Home
A32: SALE30 | B32: 45217 | C32: CUST1028 | D32: PROD5 | E32: =TRIM(Sales_fact[[#This Row],[Store_ID]]) -> STORE19 | F32: 1 | G32: =IF(ISBLANK(F32),MODE($F$2:$F$2001),F32) -> 1 | H32: 429.38 | I32: =IF(ISBLANK(H32),AVERAGE($H$2:$H$2001),H32) -> 429.38 | J32: 0.13 | K32: =IF(ISBLANK(J32),MODE($J$2:$J$2001),J32) -> 0.13 | L32: PayPal | M32: 373.5606 | N32: =G32*I32*(1-K32) -> 373.5606 | O32: =_xlfn.XLOOKUP(Sales_fact[[#This Row],[Customer_ID]],'Customer_Dim'!A:A,'Customer_Dim'!K:K,"Not Found") -> Platinum | P32: =_xlfn.XLOOKUP(Sales_fact[[#This Row],[Customer_ID]],'Customer_Dim'!A:A, 'Customer_Dim'!E:E, "Not Found") -> 27 | Q32: =VLOOKUP(Sales_fact[[#This Row],[Customer_ID]], 'Customer_Dim'!A:F, 6, FALSE) -> Female | R32: =_xlfn.XLOOKUP(Sales_fact[[#This Row],[Product_ID]],Product_Dim!A:A,Product_Dim!C:C,"OTHERS") -> Clothing
A33: SALE31 | B33: 45593 | C33: CUST1412 | D33: PROD53 | E33: =TRIM(Sales_fact[[#This Row],[Store_ID]]) -> STORE12 | F33: 2 | G33: =IF(ISBLANK(F33),MODE($F$2:$F$2001),F33) -> 2 | H33: 148.96 | I33: =IF(ISBLANK(H33),AVERAGE($H$2:$H$2001),H33) -> 148.96 | J33: 0.03 | K33: =IF(ISBLANK(J33),MODE($J$2:$J$2001),J33) -> 0.03 | L33: COD | M33: 288.9824 | N33: =G33*I33*(1-K33) -> 288.9824 | O33: =_xlfn.XLOOKUP(Sales_fact[[#This Row],[Customer_ID]],'Customer_Dim'!A:A,'Customer_Dim'!K:K,"Not Found") -> Gold | P33: =_xlfn.XLOOKUP(Sales_fact[[#This Row],[Customer_ID]],'Customer_Dim'!A:A, 'Customer_Dim'!E:E, "Not Found") -> 23 | Q33: =VLOOKUP(Sales_fact[[#This Row],[Customer_ID]], 'Customer_Dim'!A:F, 6, FALSE) -> Female | R33: =_xlfn.XLOOKUP(Sales_fact[[#This Row],[Product_ID]],Product_Dim!A:A,Product_Dim!C:C,"OTHERS") -> Clothing
A34: SALE32 | B34: 45597 | C34: CUST1398 | D34: PROD75 | E34: =TRIM(Sales_fact[[#This Row],[Store_ID]]) -> STORE8 | F34: 4 | G34: =IF(ISBLANK(F34),MODE($F$2:$F$2001),F34) -> 4 | H34: 313.83 | I34: =IF(ISBLANK(H34),AVERAGE($H$2:$H$2001),H34) -> 313.83 | J34: 0.08 | K34: =IF(ISBLANK(J34),MODE($J$2:$J$2001),J34) -> 0.08 | L34: Credit Card | M34: 1154.8944 | N34: =G34*I34*(1-K34) -> 1154.8944 | O34: =_xlfn.XLOOKUP(Sales_fact[[#This Row],[Customer_ID]],'Customer_Dim'!A:A,'Customer_Dim'!K:K,"Not Found") -> Bronze | P34: =_xlfn.XLOOKUP(Sales_fact[[#This Row],[Customer_ID]],'Customer_Dim'!A:A, 'Customer_Dim'!E:E, "Not Found") -> 54 | Q34: =VLOOKUP(Sales_fact[[#This Row],[Customer_ID]], 'Customer_Dim'!A:F, 6, FALSE) -> Male | R34: =_xlfn.XLOOKUP(Sales_fact[[#This Row],[Product_ID]],Product_Dim!A:A,Product_Dim!C:C,"OTHERS") -> Clothing
A35: SALE33 | B35: 45620 | C35: CUST1453 | D35: PROD12 | E35: =TRIM(Sales_fact[[#This Row],[Store_ID]]) -> STORE6 | F35: 2 | G35: =IF(ISBLANK(F35),MODE($F$2:$F$2001),F35) -> 2 | H35: 717.31 | I35: =IF(ISBLANK(H35),AVERAGE($H$2:$H$2001),H35) -> 717.31 | J35: 0.15 | K35: =IF(ISBLANK(J35),MODE($J$2:$J$2001),J35) -> 0.15 | L35: Credit Card | M35: 1219.427 | N35: =G35*I35*(1-K35) -> 1219.427 | O35: =_xlfn.XLOOKUP(Sales_fact[[#This Row],[Customer_ID]],'Customer_Dim'!A:A,'Customer_Dim'!K:K,"Not Found") -> Platinum | P35: =_xlfn.XLOOKUP(Sales_fact[[#This Row],[Customer_ID]],'Customer_Dim'!A:A, 'Customer_Dim'!E:E, "Not Found") -> 62 | Q35: =VLOOKUP(Sales_fact[[#This Row],[Customer_ID]], 'Customer_Dim'!A:F, 6, FALSE) -> Female | R35: =_xlfn.XLOOKUP(Sales_fact[[#This Row],[Product_ID]],Product_Dim!A:A,Product_Dim!C:C,"OTHERS") -> Beauty
A36: SALE34 | B36: 45215 | C36: CUST1344 | D36: PROD79 | E36: =TRIM(Sales_fact[[#This Row],[Store_ID]]) -> STORE1 | G36: =IF(ISBLANK(F36),MODE($F$2:$F$2001),F36) -> 2 | H36: 873.22 | I36: =IF(ISBLANK(H36),AVERAGE($H$2:$H$2001),H36) -> 873.22 | J36: 0.18 | K36: =IF(ISBLANK(J36),MODE($J$2:$J$2001),J36) -> 0.18 | L36: Credit Card | M36: 2148.1212 | N36: =G36*I36*(1-K36) -> 1432.0808 | O36: =_xlfn.XLOOKUP(Sales_fact[[#This Row],[Customer_ID]],'Customer_Dim'!A:A,'Customer_Dim'!K:K,"Not Found") -> Gold | P36: =_xlfn.XLOOKUP(Sales_fact[[#This Row],[Customer_ID]],'Customer_Dim'!A:A, 'Customer_Dim'!E:E, "Not Found") -> 39 | Q36: =VLOOKUP(Sales_fact[[#This Row],[Customer_ID]], 'Customer_Dim'!A:F, 6, FALSE) -> Male | R36: =_xlfn.XLOOKUP(Sales_fact[[#This Row],[Product_ID]],Product_Dim!A:A,Product_Dim!C:C,"OTHERS") -> Home
A37: SALE35 | B37: 45878 | C37: CUST1218 | D37: PROD16 | E37: =TRIM(Sales_fact[[#This Row],[Store_ID]]) -> STORE3 | F37: 4 | G37: =IF(ISBLANK(F37),MODE($F$2:$F$2001),F37) -> 4 | H37: 109.36 | I37: =IF(ISBLANK(H37),AVERAGE($H$2:$H$2001),H37) -> 109.36 | J37: 0.19 | K37: =IF(ISBLANK(J37),MODE($J$2:$J$2001),J37) -> 0.19 | L37: COD | M37: 354.3264 | N37: =G37*I37*(1-K37) -> 354.3264 | O37: =_xlfn.XLOOKUP(Sales_fact[[#This Row],[Customer_ID]],'Customer_Dim'!A:A,'Customer_Dim'!K:K,"Not Found") -> Platinum | P37: =_xlfn.XLOOKUP(Sales_fact[[#This Row],[Customer_ID]],'Customer_Dim'!A:A, 'Customer_Dim'!E:E, "Not Found") -> 46 | Q37: =VLOOKUP(Sales_fact[[#This Row],[Customer_ID]], 'Customer_Dim'!A:F, 6, FALSE) -> Male | R37: =_xlfn.XLOOKUP(Sales_fact[[#This Row],[Product_ID]],Product_Dim!A:A,Product_Dim!C:C,"OTHERS") -> OTHERS
A38: SALE36 | B38: 45635 | C38: CUST1086 | D38: PROD5 | E38: =TRIM(Sales_fact[[#This Row],[Store_ID]]) -> STORE7 | F38: 3 | G38: =IF(ISBLANK(F38),MODE($F$2:$F$2001),F38) -> 3 | H38: 559.52 | I38: =IF(ISBLANK(H38),AVERAGE($H$2:$H$2001),H38) -> 559.52 | J38: 0.16 | K38: =IF(ISBLANK(J38),MODE($J$2:$J$2001),J38) -> 0.16 | L38: PayPal | M38: 1409.9904 | N38: =G38*I38*(1-K38) -> 1409.9904 | O38: =_xlfn.XLOOKUP(Sales_fact[[#This Row],[Customer_ID]],'Customer_Dim'!A:A,'Customer_Dim'!K:K,"Not Found") -> Gold | P38: =_xlfn.XLOOKUP(Sales_fact[[#This Row],[Customer_ID]],'Customer_Dim'!A:A, 'Customer_Dim'!E:E, "Not Found") -> 19 | Q38: =VLOOKUP(Sales_fact[[#This Row],[Customer_ID]], 'Customer_Dim'!A:F, 6, FALSE) -> Female | R38: =_xlfn.XLOOKUP(Sales_fact[[#This Row],[Product_ID]],Product_Dim!A:A,Product_Dim!C:C,"OTHERS") -> Clothing
A39: SALE37 | B39: 45329 | C39: CUST1492 | D39: PROD10 | E39: =TRIM(Sales_fact[[#This Row],[Store_ID]]) -> STORE17 | F39: 3 | G39: =IF(ISBLANK(F39),MODE($F$2:$F$2001),F39) -> 3 | H39: 121.76 | I39: =IF(ISBLANK(H39),AVERAGE($H$2:$H$2001),H39) -> 121.76 | J39: 0.27 | K39: =IF(ISBLANK(J39),MODE($J$2:$J$2001),J39) -> 0.27 | L39: PayPal | M39: 266.6544 | N39: =G39*I39*(1-K39) -> 266.6544 | O39: =_xlfn.XLOOKUP(Sales_fact[[#This Row],[Customer_ID]],'Customer_Dim'!A:A,'Customer_Dim'!K:K,"Not Found") -> Platinum | P39: =_xlfn.XLOOKUP(Sales_fact[[#This Row],[Customer_ID]],'Customer_Dim'!A:A, 'Customer_Dim'!E:E, "Not Found") -> 59 | Q39: =VLOOKUP(Sales_fact[[#This Row],[Customer_ID]], 'Customer_Dim'!A:F, 6, FALSE) -> Female | R39: =_xlfn.XLOOKUP(Sales_fact[[#This Row],[Product_ID]],Product_Dim!A:A,Product_Dim!C:C,"OTHERS") -> Home
A40: SALE38 | B40: 45378 | C40: CUST1189 | D40: PROD33 | E40: =TRIM(Sales_fact[[#This Row],[Store_ID]]) -> STORE13 | F40: 4 | G40: =IF(ISBLANK(F40),MODE($F$2:$F$2001),F40) -> 4 | H40: 735.32 | I40: =IF(ISBLANK(H40),AVERAGE($H$2:$H$2001),H40) -> 735.32 | J40: 0.06 | K40: =IF(ISBLANK(J40),MODE($J$2:$J$2001),J40) -> 0.06 | L40: COD | M40: 2764.8032 | N40: =G40*I40*(1-K40) -> 2764.8032 | O40: =_xlfn.XLOOKUP(Sales_fact[[#This Row],[Customer_ID]],'Customer_Dim'!A:A,'Customer_Dim'!K:K,"Not Found") -> Gold | P40: =_xlfn.XLOOKUP(Sales_fact[[#This Row],[Customer_ID]],'Customer_Dim'!A:A, 'Customer_Dim'!E:E, "Not Found") -> 29 | Q40: =VLOOKUP(Sales_fact[[#This Row],[Customer_ID]], 'Customer_Dim'!A:F, 6, FALSE) -> Male | R40: =_xlfn.XLOOKUP(Sales_fact[[#This Row],[Product_ID]],Product_Dim!A:A,Product_Dim!C:C,"OTHERS") -> Home
A41: SALE39 | B41: 45264 | C41: CUST1431 | D41: PROD94 | E41: =TRIM(Sales_fact[[#This Row],[Store_ID]]) -> STORE3 | F41: 2 | G41: =IF(ISBLANK(F41),MODE($F$2:$F$2001),F41) -> 2 | H41: 600.73 | I41: =IF(ISBLANK(H41),AVERAGE($H$2:$H$2001),H41) -> 600.73 | J41: 0.08 | K41: =IF(ISBLANK(J41),MODE($J$2:$J$2001),J41) -> 0.08 | L41: Credit Card | M41: 1105.3432 | N41: =G41*I41*(1-K41) -> 1105.3432 | O41: =_xlfn.XLOOKUP(Sales_fact[[#This Row],[Customer_ID]],'Customer_Dim'!A:A,'Customer_Dim'!K:K,"Not Found") -> Platinum | P41: =_xlfn.XLOOKUP(Sales_fact[[#This Row],[Customer_ID]],'Customer_Dim'!A:A, 'Customer_Dim'!E:E, "Not Found") -> 27 | Q41: =VLOOKUP(Sales_fact[[#This Row],[Customer_ID]], 'Customer_Dim'!A:F, 6, FALSE) -> Male | R41: =_xlfn.XLOOKUP(Sales_fact[[#This Row],[Product_ID]],Product_Dim!A:A,Product_Dim!C:C,"OTHERS") -> Beauty
A42: SALE40 | B42: 45486 | C42: CUST1072 | D42: PROD26 | E42: =TRIM(Sales_fact[[#This Row],[Store_ID]]) -> STORE19 | F42: 2 | G42: =IF(ISBLANK(F42),MODE($F$2:$F$2001),F42) -> 2 | H42: 873.86 | I42: =IF(ISBLANK(H42),AVERAGE($H$2:$H$2001),H42) -> 873.86 | J42: 0.07 | K42: =IF(ISBLANK(J42),MODE($J$2:$J$2001),J42) -> 0.07 | L42: COD | M42: 1625.3796 | N42: =G42*I42*(1-K42) -> 1625.3796 | O42: =_xlfn.XLOOKUP(Sales_fact[[#This Row],[Customer_ID]],'Customer_Dim'!A:A,'Customer_Dim'!K:K,"Not Found") -> Gold | P42: =_xlfn.XLOOKUP(Sales_fact[[#This Row],[Customer_ID]],'Customer_Dim'!A:A, 'Customer_Dim'!E:E, "Not Found") -> 39 | Q42: =VLOOKUP(Sales_fact[[#This Row],[Customer_ID]], 'Customer_Dim'!A:F, 6, FALSE) -> Female | R42: =_xlfn.XLOOKUP(Sales_fact[[#This Row],[Product_ID]],Product_Dim!A:A,Product_Dim!C:C,"OTHERS") -> Electronics
A43: SALE41 | B43: 45241 | C43: CUST1302 | D43: PROD23 | E43: =TRIM(Sales_fact[[#This Row],[Store_ID]]) -> STORE8 | F43: 3 | G43: =IF(ISBLANK(F43),MODE($F$2:$F$2001),F43) -> 3 | H43: 342.47 | I43: =IF(ISBLANK(H43),AVERAGE($H$2:$H$2001),H43) -> 342.47 | J43: 0.08 | K43: =IF(ISBLANK(J43),MODE($J$2:$J$2001),J43) -> 0.08 | L43: PayPal | M43: 945.2172 | N43: =G43*I43*(1-K43) -> 945.2172 | O43: =_xlfn.XLOOKUP(Sales_fact[[#This Row],[Customer_ID]],'Customer_Dim'!A:A,'Customer_Dim'!K:K,"Not Found") -> Gold | P43: =_xlfn.XLOOKUP(Sales_fact[[#This Row],[Customer_ID]],'Customer_Dim'!A:A, 'Customer_Dim'!E:E, "Not Found") -> 36 | Q43: =VLOOKUP(Sales_fact[[#This Row],[Customer_ID]], 'Customer_Dim'!A:F, 6, FALSE) -> Male | R43: =_xlfn.XLOOKUP(Sales_fact[[#This Row],[Product_ID]],Product_Dim!A:A,Product_Dim!C:C,"OTHERS") -> Clothing
A44: SALE42 | B44: 45649 | C44: CUST1335 | D44: PROD29 | E44: =TRIM(Sales_fact[[#This Row],[Store_ID]]) -> STORE9 | F44: 2 | G44: =IF(ISBLANK(F44),MODE($F$2:$F$2001),F44) -> 2 | H44: 915.15 | I44: =IF(ISBLANK(H44),AVERAGE($H$2:$H$2001),H44) -> 915.15 | J44: 0.16 | K44: =IF(ISBLANK(J44),MODE($J$2:$J$2001),J44) -> 0.16 | L44: PayPal | M44: 1537.452 | N44: =G44*I44*(1-K44) -> 1537.452 | O44: =_xlfn.XLOOKUP(Sales_fact[[#This Row],[Customer_ID]],'Customer_Dim'!A:A,'Customer_Dim'!K:K,"Not Found") -> Platinum | P44: =_xlfn.XLOOKUP(Sales_fact[[#This Row],[Customer_ID]],'Customer_Dim'!A:A, 'Customer_Dim'!E:E, "Not Found") -> 37 | Q44: =VLOOKUP(Sales_fact[[#This Row],[Customer_ID]], 'Customer_Dim'!A:F, 6, FALSE) -> Male | R44: =_xlfn.XLOOKUP(Sales_fact[[#This Row],[Product_ID]],Product_Dim!A:A,Product_Dim!C:C,"OTHERS") -> Home
A45: SALE43 | B45: 45677 | C45: CUST1084 | D45: PROD33 | E45: =TRIM(Sales_fact[[#This Row],[Store_ID]]) -> STORE17 | G45: =IF(ISBLANK(F45),MODE($F$2:$F$2001),F45) -> 2 | H45: 863.11 | I45: =IF(ISBLANK(H45),AVERAGE($H$2:$H$2001),H45) -> 863.11 | J45: 0.28 | K45: =IF(ISBLANK(J45),MODE($J$2:$J$2001),J45) -> 0.28 | L45: PayPal | M45: 1864.3176 | N45: =G45*I45*(1-K45) -> 1242.8784 | O45: =_xlfn.XLOOKUP(Sales_fact[[#This Row],[Customer_ID]],'Customer_Dim'!A:A,'Customer_Dim'!K:K,"Not Found") -> Platinum | P45: =_xlfn.XLOOKUP(Sales_fact[[#This Row],[Customer_ID]],'Customer_Dim'!A:A, 'Customer_Dim'!E:E, "Not Found") -> 26 | Q45: =VLOOKUP(Sales_fact[[#This Row],[Customer_ID]], 'Customer_Dim'!A:F, 6, FALSE) -> Female | R45: =_xlfn.XLOOKUP(Sales_fact[[#This Row],[Product_ID]],Product_Dim!A:A,Product_Dim!C:C,"OTHERS") -> Home
A46: SALE44 | B46: 45538 | C46: CUST1203 | D46: PROD43 | E46: =TRIM(Sales_fact[[#This Row],[Store_ID]]) -> STORE12 | F46: 2 | G46: =IF(ISBLANK(F46),MODE($F$2:$F$2001),F46) -> 2 | H46: 209.32 | I46: =IF(ISBLANK(H46),AVERAGE($H$2:$H$2001),H46) -> 209.32 | J46: 0.23 | K46: =IF(ISBLANK(J46),MODE($J$2:$J$2001),J46) -> 0.23 | L46: COD | M46: 322.3528 | N46: =G46*I46*(1-K46) -> 322.3528 | O46: =_xlfn.XLOOKUP(Sales_fact[[#This Row],[Customer_ID]],'Customer_Dim'!A:A,'Customer_Dim'!K:K,"Not Found") -> Platinum | P46: =_xlfn.XLOOKUP(Sales_fact[[#This Row],[Customer_ID]],'Customer_Dim'!A:A, 'Customer_Dim'!E:E, "Not Found") -> 47 | Q46: =VLOOKUP(Sales_fact[[#This Row],[Customer_ID]], 'Customer_Dim'!A:F, 6, FALSE) -> Male | R46: =_xlfn.XLOOKUP(Sales_fact[[#This Row],[Product_ID]],Product_Dim!A:A,Product_Dim!C:C,"OTHERS") -> Electronics
A47: SALE45 | B47: 45606 | C47: CUST1470 | D47: PROD59 | E47: =TRIM(Sales_fact[[#This Row],[Store_ID]]) -> STORE8 | F47: 4 | G47: =IF(ISBLANK(F47),MODE($F$2:$F$2001),F47) -> 4 | H47: 288.6 | I47: =IF(ISBLANK(H47),AVERAGE($H$2:$H$2001),H47) -> 288.6 | J47: 0.09 | K47: =IF(ISBLANK(J47),MODE($J$2:$J$2001),J47) -> 0.09 | L47: PayPal | M47: 1050.504 | N47: =G47*I47*(1-K47) -> 1050.504 | O47: =_xlfn.XLOOKUP(Sales_fact[[#This Row],[Customer_ID]],'Customer_Dim'!A:A,'Customer_Dim'!K:K,"Not Found") -> Gold | P47: =_xlfn.XLOOKUP(Sales_fact[[#This Row],[Customer_ID]],'Customer_Dim'!A:A, 'Customer_Dim'!E:E, "Not Found") -> 21 | Q47: =VLOOKUP(Sales_fact[[#This Row],[Customer_ID]], 'Customer_Dim'!A:F, 6, FALSE) -> Female | R47: =_xlfn.XLOOKUP(Sales_fact[[#This Row],[Product_ID]],Product_Dim!A:A,Product_Dim!C:C,"OTHERS") -> Beauty
A48: SALE46 | B48: 45570 | C48: CUST1070 | D48: PROD78 | E48: =TRIM(Sales_fact[[#This Row],[Store_ID]]) -> STORE16 | F48: 1 | G48: =IF(ISBLANK(F48),MODE($F$2:$F$2001),F48) -> 1 | H48: 418.69 | I48: =IF(ISBLANK(H48),AVERAGE($H$2:$H$2001),H48) -> 418.69 | J48: 0.06 | K48: =IF(ISBLANK(J48),MODE($J$2:$J$2001),J48) -> 0.06 | L48: PayPal | M48: 393.5686 | N48: =G48*I48*(1-K48) -> 393.5686 | O48: =_xlfn.XLOOKUP(Sales_fact[[#This Row],[Customer_ID]],'Customer_Dim'!A:A,'Customer_Dim'!K:K,"Not Found") -> Gold | P48: =_xlfn.XLOOKUP(Sales_fact[[#This Row],[Customer_ID]],'Customer_Dim'!A:A, 'Customer_Dim'!E:E, "Not Found") -> 29 | Q48: =VLOOKUP(Sales_fact[[#This Row],[Customer_ID]], 'Customer_Dim'!A:F, 6, FALSE) -> Female | R48: =_xlfn.XLOOKUP(Sales_fact[[#This Row],[Product_ID]],Product_Dim!A:A,Product_Dim!C:C,"OTHERS") -> Home
A49: SALE47 | B49: 45466 | C49: CUST1008 | D49: PROD30 | E49: =TRIM(Sales_fact[[#This Row],[Store_ID]]) -> STORE11 | F49: 1 | G49: =IF(ISBLANK(F49),MODE($F$2:$F$2001),F49) -> 1 | H49: 135.78 | I49: =IF(ISBLANK(H49),AVERAGE($H$2:$H$2001),H49) -> 135.78 | J49: 0.14 | K49: =IF(ISBLANK(J49),MODE($J$2:$J$2001),J49) -> 0.14 | L49: PayPal | M49: 116.7708 | N49: =G49*I49*(1-K49) -> 116.7708 | O49: =_xlfn.XLOOKUP(Sales_fact[[#This Row],[Customer_ID]],'Customer_Dim'!A:A,'Customer_Dim'!K:K,"Not Found") -> Gold | P49: =_xlfn.XLOOKUP(Sales_fact[[#This Row],[Customer_ID]],'Customer_Dim'!A:A, 'Customer_Dim'!E:E, "Not Found") -> 53 | Q49: =VLOOKUP(Sales_fact[[#This Row],[Customer_ID]], 'Customer_Dim'!A:F, 6, FALSE) -> Female | R49: =_xlfn.XLOOKUP(Sales_fact[[#This Row],[Product_ID]],Product_Dim!A:A,Product_Dim!C:C,"OTHERS") -> Home
A50: SALE48 | B50: 45218 | C50: CUST1203 | D50: PROD44 | E50: =TRIM(Sales_fact[[#This Row],[Store_ID]]) -> STORE17 | F50: 1 | G50: =IF(ISBLANK(F50),MODE($F$2:$F$2001),F50) -> 1 | H50: 517.13 | I50: =IF(ISBLANK(H50),AVERAGE($H$2:$H$2001),H50) -> 517.13 | J50: 0.28 | K50: =IF(ISBLANK(J50),MODE($J$2:$J$2001),J50) -> 0.28 | L50: Credit Card | M50: 372.3336 | N50: =G50*I50*(1-K50) -> 372.3336 | O50: =_xlfn.XLOOKUP(Sales_fact[[#This Row],[Customer_ID]],'Customer_Dim'!A:A,'Customer_Dim'!K:K,"Not Found") -> Platinum | P50: =_xlfn.XLOOKUP(Sales_fact[[#This Row],[Customer_ID]],'Customer_Dim'!A:A, 'Customer_Dim'!E:E, "Not Found") -> 47 | Q50: =VLOOKUP(Sales_fact[[#This Row],[Customer_ID]], 'Customer_Dim'!A:F, 6, FALSE) -> Male | R50: =_xlfn.XLOOKUP(Sales_fact[[#This Row],[Product_ID]],Product_Dim!A:A,Product_Dim!C:C,"OTHERS") -> Sports
A51: SALE49 | B51: 45607 | C51: CUST1420 | D51: PROD21 | E51: =TRIM(Sales_fact[[#This Row],[Store_ID]]) -> STORE16 | F51: 2 | G51: =IF(ISBLANK(F51),MODE($F$2:$F$2001),F51) -> 2 | H51: 384.66 | I51: =IF(ISBLANK(H51),AVERAGE($H$2:$H$2001),H51) -> 384.66 | J51: 0.08 | K51: =IF(ISBLANK(J51),MODE($J$2:$J$2001),J51) -> 0.08 | L51: COD | M51: 707.7744 | N51: =G51*I51*(1-K51) -> 707.7744 | O51: =_xlfn.XLOOKUP(Sales_fact[[#This Row],[Customer_ID]],'Customer_Dim'!A:A,'Customer_Dim'!K:K,"Not Found") -> Bronze | P51: =_xlfn.XLOOKUP(Sales_fact[[#This Row],[Customer_ID]],'Customer_Dim'!A:A, 'Customer_Dim'!E:E, "Not Found") -> 60 | Q51: =VLOOKUP(Sales_fact[[#This Row],[Customer_ID]], 'Customer_Dim'!A:F, 6, FALSE) -> Male | R51: =_xlfn.XLOOKUP(Sales_fact[[#This Row],[Product_ID]],Product_Dim!A:A,Product_Dim!C:C,"OTHERS") -> Home
A52: SALE50 | B52: 45291 | C52: CUST1070 | D52: PROD52 | E52: =TRIM(Sales_fact[[#This Row],[Store_ID]]) -> STORE9 | F52: 3 | G52: =IF(ISBLANK(F52),MODE($F$2:$F$2001),F52) -> 3 | H52: 83.7 | I52: =IF(ISBLANK(H52),AVERAGE($H$2:$H$2001),H52) -> 83.7 | J52: 0.24 | K52: =IF(ISBLANK(J52),MODE($J$2:$J$2001),J52) -> 0.24 | L52: PayPal | M52: 190.836 | N52: =G52*I52*(1-K52) -> 190.836 | O52: =_xlfn.XLOOKUP(Sales_fact[[#This Row],[Customer_ID]],'Customer_Dim'!A:A,'Customer_Dim'!K:K,"Not Found") -> Gold | P52: =_xlfn.XLOOKUP(Sales_fact[[#This Row],[Customer_ID]],'Customer_Dim'!A:A, 'Customer_Dim'!E:E, "Not Found") -> 29 | Q52: =VLOOKUP(Sales_fact[[#This Row],[Customer_ID]], 'Customer_Dim'!A:F, 6, FALSE) -> Female | R52: =_xlfn.XLOOKUP(Sales_fact[[#This Row],[Product_ID]],Product_Dim!A:A,Product_Dim!C:C,"OTHERS") -> Sports
A53: SALE51 | B53: 45689 | C53: CUST1142 | D53: PROD69 | E53: =TRIM(Sales_fact[[#This Row],[Store_ID]]) -> STORE7 | F53: 3 | G53: =IF(ISBLANK(F53),MODE($F$2:$F$2001),F53) -> 3 | H53: 76.57 | I53: =IF(ISBLANK(H53),AVERAGE($H$2:$H$2001),H53) -> 76.57 | J53: 0.26 | K53: =IF(ISBLANK(J53),MODE($J$2:$J$2001),J53) -> 0.26 | L53: Credit Card | M53: 169.9854 | N53: =G53*I53*(1-K53) -> 169.9854 | O53: =_xlfn.XLOOKUP(Sales_fact[[#This Row],[Customer_ID]],'Customer_Dim'!A:A,'Customer_Dim'!K:K,"Not Found") -> Bronze | P53: =_xlfn.XLOOKUP(Sales_fact[[#This Row],[Customer_ID]],'Customer_Dim'!A:A, 'Customer_Dim'!E:E, "Not Found") -> 37 | Q53: =VLOOKUP(Sales_fact[[#This Row],[Customer_ID]], 'Customer_Dim'!A:F, 6, FALSE) -> Male | R53: =_xlfn.XLOOKUP(Sales_fact[[#This Row],[Product_ID]],Product_Dim!A:A,Product_Dim!C:C,"OTHERS") -> Clothing
A54: SALE52 | B54: 45894 | C54: CUST1148 | D54: PROD89 | E54: =TRIM(Sales_fact[[#This Row],[Store_ID]]) -> STORE6 | F54: 3 | G54: =IF(ISBLANK(F54),MODE($F$2:$F$2001),F54) -> 3 | I54: =IF(ISBLANK(H54),AVERAGE($H$2:$H$2001),H54) -> 513.98477 | K54: =IF(ISBLANK(J54),MODE($J$2:$J$2001),J54) -> 0.1 | L54: Credit Card | M54: 486.0633 | N54: =G54*I54*(1-K54) -> 1387.7589 | O54: =_xlfn.XLOOKUP(Sales_fact[[#This Row],[Customer_ID]],'Customer_Dim'!A:A,'Customer_Dim'!K:K,"Not Found") -> Bronze | P54: =_xlfn.XLOOKUP(Sales_fact[[#This Row],[Customer_ID]],'Customer_Dim'!A:A, 'Customer_Dim'!E:E, "Not Found") -> 42 | Q54: =VLOOKUP(Sales_fact[[#This Row],[Customer_ID]], 'Customer_Dim'!A:F, 6, FALSE) -> Female | R54: =_xlfn.XLOOKUP(Sales_fact[[#This Row],[Product_ID]],Product_Dim!A:A,Product_Dim!C:C,"OTHERS") -> Beauty
A55: SALE53 | B55: 45677 | C55: CUST1324 | D55: PROD20 | E55: =TRIM(Sales_fact[[#This Row],[Store_ID]]) -> STORE8 | F55: 1 | G55: =IF(ISBLANK(F55),MODE($F$2:$F$2001),F55) -> 1 | H55: 900.35 | I55: =IF(ISBLANK(H55),AVERAGE($H$2:$H$2001),H55) -> 900.35 | J55: 0.13 | K55: =IF(ISBLANK(J55),MODE($J$2:$J$2001),J55) -> 0.13 | L55: COD | M55: 783.3045 | N55: =G55*I55*(1-K55) -> 783.3045 | O55: =_xlfn.XLOOKUP(Sales_fact[[#This Row],[Customer_ID]],'Customer_Dim'!A:A,'Customer_Dim'!K:K,"Not Found") -> Bronze | P55: =_xlfn.XLOOKUP(Sales_fact[[#This Row],[Customer_ID]],'Customer_Dim'!A:A, 'Customer_Dim'!E:E, "Not Found") -> 58 | Q55: =VLOOKUP(Sales_fact[[#This Row],[Customer_ID]], 'Customer_Dim'!A:F, 6, FALSE) -> Male | R55: =_xlfn.XLOOKUP(Sales_fact[[#This Row],[Product_ID]],Product_Dim!A:A,Product_Dim!C:C,"OTHERS") -> Sports
A56: SALE54 | B56: 45706 | C56: CUST1095 | D56: PROD40 | E56: =TRIM(Sales_fact[[#This Row],[Store_ID]]) -> STORE10 | F56: 4 | G56: =IF(ISBLANK(F56),MODE($F$2:$F$2001),F56) -> 4 | H56: 428.09 | I56: =IF(ISBLANK(H56),AVERAGE($H$2:$H$2001),H56) -> 428.09 | J56: 0.07 | K56: =IF(ISBLANK(J56),MODE($J$2:$J$2001),J56) -> 0.07 | L56: Credit Card | M56: 1592.4948 | N56: =G56*I56*(1-K56) -> 1592.4948 | O56: =_xlfn.XLOOKUP(Sales_fact[[#This Row],[Customer_ID]],'Customer_Dim'!A:A,'Customer_Dim'!K:K,"Not Found") -> Platinum | P56: =_xlfn.XLOOKUP(Sales_fact[[#This Row],[Customer_ID]],'Customer_Dim'!A:A, 'Customer_Dim'!E:E, "Not Found") -> 62 | Q56: =VLOOKUP(Sales_fact[[#This Row],[Customer_ID]], 'Customer_Dim'!A:F, 6, FALSE) -> Female | R56: =_xlfn.XLOOKUP(Sales_fact[[#This Row],[Product_ID]],Product_Dim!A:A,Product_Dim!C:C,"OTHERS") -> Electronics
A57: SALE55 | B57: 45589 | C57: CUST1416 | D57: PROD49 | E57: =TRIM(Sales_fact[[#This Row],[Store_ID]]) -> STORE11 | F57: 2 | G57: =IF(ISBLANK(F57),MODE($F$2:$F$2001),F57) -> 2 | H57: 559.71 | I57: =IF(ISBLANK(H57),AVERAGE($H$2:$H$2001),H57) -> 559.71 | J57: 0.3 | K57: =IF(ISBLANK(J57),MODE($J$2:$J$2001),J57) -> 0.3 | L57: COD | M57: 783.594 | N57: =G57*I57*(1-K57) -> 783.594 | O57: =_xlfn.XLOOKUP(Sales_fact[[#This Row],[Customer_ID]],'Customer_Dim'!A:A,'Customer_Dim'!K:K,"Not Found") -> Platinum | P57: =_xlfn.XLOOKUP(Sales_fact[[#This Row],[Customer_ID]],'Customer_Dim'!A:A, 'Customer_Dim'!E:E, "Not Found") -> 46 | Q57: =VLOOKUP(Sales_fact[[#This Row],[Customer_ID]], 'Customer_Dim'!A:F, 6, FALSE) -> Male | R57: =_xlfn.XLOOKUP(Sales_fact[[#This Row],[Product_ID]],Product_Dim!A:A,Product_Dim!C:C,"OTHERS") -> Beauty
A58: SALE56 | B58: 45282 | C58: CUST1080 | D58: PROD34 | E58: =TRIM(Sales_fact[[#This Row],[Store_ID]]) -> STORE6 | F58: 2 | G58: =IF(ISBLANK(F58),MODE($F$2:$F$2001),F58) -> 2 | H58: 833.7 | I58: =IF(ISBLANK(H58),AVERAGE($H$2:$H$2001),H58) -> 833.7 | J58: 0.06 | K58: =IF(ISBLANK(J58),MODE($J$2:$J$2001),J58) -> 0.06 | L58: PayPal | M58: 1567.356 | N58: =G58*I58*(1-K58) -> 1567.356 | O58: =_xlfn.XLOOKUP(Sales_fact[[#This Row],[Customer_ID]],'Customer_Dim'!A:A,'Customer_Dim'!K:K,"Not Found") -> Bronze | P58: =_xlfn.XLOOKUP(Sales_fact[[#This Row],[Customer_ID]],'Customer_Dim'!A:A, 'Customer_Dim'!E:E, "Not Found") -> 61 | Q58: =VLOOKUP(Sales_fact[[#This Row],[Customer_ID]], 'Customer_Dim'!A:F, 6, FALSE) -> Female | R58: =_xlfn.XLOOKUP(Sales_fact[[#This Row],[Product_ID]],Product_Dim!A:A,Product_Dim!C:C,"OTHERS") -> Electronics
A59: SALE57 | B59: 45462 | C59: CUST1467 | D59: PROD47 | E59: =TRIM(Sales_fact[[#This Row],[Store_ID]]) -> STORE14 | F59: 2 | G59: =IF(ISBLANK(F59),MODE($F$2:$F$2001),F59) -> 2 | H59: 680.16 | I59: =IF(ISBLANK(H59),AVERAGE($H$2:$H$2001),H59) -> 680.16 | J59: 0.28 | K59: =IF(ISBLANK(J59),MODE($J$2:$J$2001),J59) -> 0.28 | L59: Credit Card | M59: 979.4304 | N59: =G59*I59*(1-K59) -> 979.4304 | O59: =_xlfn.XLOOKUP(Sales_fact[[#This Row],[Customer_ID]],'Customer_Dim'!A:A,'Customer_Dim'!K:K,"Not Found") -> Gold | P59: =_xlfn.XLOOKUP(Sales_fact[[#This Row],[Customer_ID]],'Customer_Dim'!A:A, 'Customer_Dim'!E:E, "Not Found") -> 63 | Q59: =VLOOKUP(Sales_fact[[#This Row],[Customer_ID]], 'Customer_Dim'!A:F, 6, FALSE) -> Female | R59: =_xlfn.XLOOKUP(Sales_fact[[#This Row],[Product_ID]],Product_Dim!A:A,Product_Dim!C:C,"OTHERS") -> Beauty
A60: SALE58 | B60: 45633 | C60: CUST1404 | D60: PROD15 | E60: =TRIM(Sales_fact[[#This Row],[Store_ID]]) -> STORE7 | F60: 4 | G60: =IF(ISBLANK(F60),MODE($F$2:$F$2001),F60) -> 4 | H60: 733.42 | I60: =IF(ISBLANK(H60),AVERAGE($H$2:$H$2001),H60) -> 733.42 | K60: =IF(ISBLANK(J60),MODE($J$2:$J$2001),J60) -> 0.1 | L60: PayPal | M60: 2552.3016 | N60: =G60*I60*(1-K60) -> 2640.312 | O60: =_xlfn.XLOOKUP(Sales_fact[[#This Row],[Customer_ID]],'Customer_Dim'!A:A,'Customer_Dim'!K:K,"Not Found") -> Silver | P60: =_xlfn.XLOOKUP(Sales_fact[[#This Row],[Customer_ID]],'Customer_Dim'!A:A, 'Customer_Dim'!E:E, "Not Found") -> 22 | Q60: =VLOOKUP(Sales_fact[[#This Row],[Customer_ID]], 'Customer_Dim'!A:F, 6, FALSE) -> Female | R60: =_xlfn.XLOOKUP(Sales_fact[[#This Row],[Product_ID]],Product_Dim!A:A,Product_Dim!C:C,"OTHERS") -> Electronics
A61: SALE59 | B61: 45257 | C61: CUST1367 | D61: PROD89 | E61: =TRIM(Sales_fact[[#This Row],[Store_ID]]) -> STORE11 | F61: 1 | G61: =IF(ISBLANK(F61),MODE($F$2:$F$2001),F61) -> 1 | H61: 996.33 | I61: =IF(ISBLANK(H61),AVERAGE($H$2:$H$2001),H61) -> 996.33 | J61: 0.23 | K61: =IF(ISBLANK(J61),MODE($J$2:$J$2001),J61) -> 0.23 | L61: PayPal | M61: 767.1741 | N61: =G61*I61*(1-K61) -> 767.1741 | O61: =_xlfn.XLOOKUP(Sales_fact[[#This Row],[Customer_ID]],'Customer_Dim'!A:A,'Customer_Dim'!K:K,"Not Found") -> Bronze | P61: =_xlfn.XLOOKUP(Sales_fact[[#This Row],[Customer_ID]],'Customer_Dim'!A:A, 'Customer_Dim'!E:E, "Not Found") -> 51 | Q61: =VLOOKUP(Sales_fact[[#This Row],[Customer_ID]], 'Customer_Dim'!A:F, 6, FALSE) -> Male | R61: =_xlfn.XLOOKUP(Sales_fact[[#This Row],[Product_ID]],Product_Dim!A:A,Product_Dim!C:C,"OTHERS") -> Beauty
A62: SALE60 | B62: 45854 | C62: CUST1408 | D62: PROD31 | E62: =TRIM(Sales_fact[[#This Row],[Store_ID]]) -> STORE10 | F62: 1 | G62: =IF(ISBLANK(F62),MODE($F$2:$F$2001),F62) -> 1 | H62: 198.83 | I62: =IF(ISBLANK(H62),AVERAGE($H$2:$H$2001),H62) -> 198.83 | J62: 0.09 | K62: =IF(ISBLANK(J62),MODE($J$2:$J$2001),J62) -> 0.09 | L62: COD | M62: 180.9353 | N62: =G62*I62*(1-K62) -> 180.9353 | O62: =_xlfn.XLOOKUP(Sales_fact[[#This Row],[Customer_ID]],'Customer_Dim'!A:A,'Customer_Dim'!K:K,"Not Found") -> Gold | P62: =_xlfn.XLOOKUP(Sales_fact[[#This Row],[Customer_ID]],'Customer_Dim'!A:A, 'Customer_Dim'!E:E, "Not Found") -> 36 | Q62: =VLOOKUP(Sales_fact[[#This Row],[Customer_ID]], 'Customer_Dim'!A:F, 6, FALSE) -> Male | R62: =_xlfn.XLOOKUP(Sales_fact[[#This Row],[Product_ID]],Product_Dim!A:A,Product_Dim!C:C,"OTHERS") -> Sports
A63: SALE61 | B63: 45716 | C63: CUST1239 | D63: PROD19 | E63: =TRIM(Sales_fact[[#This Row],[Store_ID]]) -> STORE7 | F63: 1 | G63: =IF(ISBLANK(F63),MODE($F$2:$F$2001),F63) -> 1 | H63: 374.92 | I63: =IF(ISBLANK(H63),AVERAGE($H$2:$H$2001),H63) -> 374.92 | J63: 0.18 | K63: =IF(ISBLANK(J63),MODE($J$2:$J$2001),J63) -> 0.18 | L63: PayPal | M63: 307.4344 | N63: =G63*I63*(1-K63) -> 307.4344 | O63: =_xlfn.XLOOKUP(Sales_fact[[#This Row],[Customer_ID]],'Customer_Dim'!A:A,'Customer_Dim'!K:K,"Not Found") -> Platinum | P63: =_xlfn.XLOOKUP(Sales_fact[[#This Row],[Customer_ID]],'Customer_Dim'!A:A, 'Customer_Dim'!E:E, "Not Found") -> 58 | Q63: =VLOOKUP(Sales_fact[[#This Row],[Customer_ID]], 'Customer_Dim'!A:F, 6, FALSE) -> Female | R63: =_xlfn.XLOOKUP(Sales_fact[[#This Row],[Product_ID]],Product_Dim!A:A,Product_Dim!C:C,"OTHERS") -> Sports
A64: SALE62 | B64: 45515 | C64: CUST1464 | D64: PROD93 | E64: =TRIM(Sales_fact[[#This Row],[Store_ID]]) -> STORE16 | F64: 1 | G64: =IF(ISBLANK(F64),MODE($F$2:$F$2001),F64) -> 1 | H64: 468.94 | I64: =IF(ISBLANK(H64),AVERAGE($H$2:$H$2001),H64) -> 468.94 | J64: 0.12 | K64: =IF(ISBLANK(J64),MODE($J$2:$J$2001),J64) -> 0.12 | L64: Credit Card | M64: 412.6672 | N64: =G64*I64*(1-K64) -> 412.6672 | O64: =_xlfn.XLOOKUP(Sales_fact[[#This Row],[Customer_ID]],'Customer_Dim'!A:A,'Customer_Dim'!K:K,"Not Found") -> Not Found | P64: =_xlfn.XLOOKUP(Sales_fact[[#This Row],[Customer_ID]],'Customer_Dim'!A:A, 'Customer_Dim'!E:E, "Not Found") -> Not Found | Q64: =VLOOKUP(Sales_fact[[#This Row],[Customer_ID]], 'Customer_Dim'!A:F, 6, FALSE) -> #N/A | R64: =_xlfn.XLOOKUP(Sales_fact[[#This Row],[Product_ID]],Product_Dim!A:A,Product_Dim!C:C,"OTHERS") -> Electronics
A65: SALE63 | B65: 45927 | C65: CUST1126 | D65: PROD89 | E65: =TRIM(Sales_fact[[#This Row],[Store_ID]]) -> STORE12 | F65: 2 | G65: =IF(ISBLANK(F65),MODE($F$2:$F$2001),F65) -> 2 | H65: 121.37 | I65: =IF(ISBLANK(H65),AVERAGE($H$2:$H$2001),H65) -> 121.37 | J65: 0.05 | K65: =IF(ISBLANK(J65),MODE($J$2:$J$2001),J65) -> 0.05 | L65: Credit Card | M65: 230.603 | N65: =G65*I65*(1-K65) -> 230.603 | O65: =_xlfn.XLOOKUP(Sales_fact[[#This Row],[Customer_ID]],'Customer_Dim'!A:A,'Customer_Dim'!K:K,"Not Found") -> Gold | P65: =_xlfn.XLOOKUP(Sales_fact[[#This Row],[Customer_ID]],'Customer_Dim'!A:A, 'Customer_Dim'!E:E, "Not Found") -> 62 | Q65: =VLOOKUP(Sales_fact[[#This Row],[Customer_ID]], 'Customer_Dim'!A:F, 6, FALSE) -> Female | R65: =_xlfn.XLOOKUP(Sales_fact[[#This Row],[Product_ID]],Product_Dim!A:A,Product_Dim!C:C,"OTHERS") -> Beauty
A66: SALE64 | B66: 45914 | C66: CUST1255 | D66: PROD53 | E66: =TRIM(Sales_fact[[#This Row],[Store_ID]]) -> STORE10 | F66: 3 | G66: =IF(ISBLANK(F66),MODE($F$2:$F$2001),F66) -> 3 | H66: 480.06 | I66: =IF(ISBLANK(H66),AVERAGE($H$2:$H$2001),H66) -> 480.06 | J66: 0.01 | K66: =IF(ISBLANK(J66),MODE($J$2:$J$2001),J66) -> 0.01 | L66: Credit Card | N66: =G66*I66*(1-K66) -> 1425.7782 | O66: =_xlfn.XLOOKUP(Sales_fact[[#This Row],[Customer_ID]],'Customer_Dim'!A:A,'Customer_Dim'!K:K,"Not Found") -> Gold | P66: =_xlfn.XLOOKUP(Sales_fact[[#This Row],[Customer_ID]],'Customer_Dim'!A:A, 'Customer_Dim'!E:E, "Not Found") -> 21 | Q66: =VLOOKUP(Sales_fact[[#This Row],[Customer_ID]], 'Customer_Dim'!A:F, 6, FALSE) -> Male | R66: =_xlfn.XLOOKUP(Sales_fact[[#This Row],[Product_ID]],Product_Dim!A:A,Product_Dim!C:C,"OTHERS") -> Clothing
A67: SALE65 | B67: 45290 | C67: CUST1162 | D67: PROD99 | E67: =TRIM(Sales_fact[[#This Row],[Store_ID]]) -> STORE17 | F67: 2 | G67: =IF(ISBLANK(F67),MODE($F$2:$F$2001),F67) -> 2 | H67: 856.57 | I67: =IF(ISBLANK(H67),AVERAGE($H$2:$H$2001),H67) -> 856.57 | J67: 0.24 | K67: =IF(ISBLANK(J67),MODE($J$2:$J$2001),J67) -> 0.24 | L67: Credit Card | M67: 1301.9864 | N67: =G67*I67*(1-K67) -> 1301.9864 | O67: =_xlfn.XLOOKUP(Sales_fact[[#This Row],[Customer_ID]],'Customer_Dim'!A:A,'Customer_Dim'!K:K,"Not Found") -> Silver | P67: =_xlfn.XLOOKUP(Sales_fact[[#This Row],[Customer_ID]],'Customer_Dim'!A:A, 'Customer_Dim'!E:E, "Not Found") -> 37 | Q67: =VLOOKUP(Sales_fact[[#This Row],[Customer_ID]], 'Customer_Dim'!A:F, 6, FALSE) -> Male | R67: =_xlfn.XLOOKUP(Sales_fact[[#This Row],[Product_ID]],Product_Dim!A:A,Product_Dim!C:C,"OTHERS") -> Home
A68: SALE66 | B68: 45213 | C68: CUST1269 | D68: PROD77 | E68: =TRIM(Sales_fact[[#This Row],[Store_ID]]) -> STORE2 | F68: 4 | G68: =IF(ISBLANK(F68),MODE($F$2:$F$2001),F68) -> 4 | H68: 814.25 | I68: =IF(ISBLANK(H68),AVERAGE($H$2:$H$2001),H68) -> 814.25 | J68: 0.18 | K68: =IF(ISBLANK(J68),MODE($J$2:$J$2001),J68) -> 0.18 | L68: Credit Card | M68: 2670.74 | N68: =G68*I68*(1-K68) -> 2670.74 | O68: =_xlfn.XLOOKUP(Sales_fact[[#This Row],[Customer_ID]],'Customer_Dim'!A:A,'Customer_Dim'!K:K,"Not Found") -> Silver | P68: =_xlfn.XLOOKUP(Sales_fact[[#This Row],[Customer_ID]],'Customer_Dim'!A:A, 'Customer_Dim'!E:E, "Not Found") -> 45 | Q68: =VLOOKUP(Sales_fact[[#This Row],[Customer_ID]], 'Customer_Dim'!A:F, 6, FALSE) -> Female | R68: =_xlfn.XLOOKUP(Sales_fact[[#This Row],[Product_ID]],Product_Dim!A:A,Product_Dim!C:C,"OTHERS") -> Electronics
A69: SALE67 | B69: 45255 | C69: CUST1483 | D69: PROD12 | E69: =TRIM(Sales_fact[[#This Row],[Store_ID]]) -> STORE2 | F69: 1 | G69: =IF(ISBLANK(F69),MODE($F$2:$F$2001),F69) -> 1 | H69: 989.17 | I69: =IF(ISBLANK(H69),AVERAGE($H$2:$H$2001),H69) -> 989.17 | J69: 0.2 | K69: =IF(ISBLANK(J69),MODE($J$2:$J$2001),J69) -> 0.2 | L69: PayPal | M69: 791.336 | N69: =G69*I69*(1-K69) -> 791.336 | O69: =_xlfn.XLOOKUP(Sales_fact[[#This Row],[Customer_ID]],'Customer_Dim'!A:A,'Customer_Dim'!K:K,"Not Found") -> Gold | P69: =_xlfn.XLOOKUP(Sales_fact[[#This Row],[Customer_ID]],'Customer_Dim'!A:A, 'Customer_Dim'!E:E, "Not Found") -> 48 | Q69: =VLOOKUP(Sales_fact[[#This Row],[Customer_ID]], 'Customer_Dim'!A:F, 6, FALSE) -> Male | R69: =_xlfn.XLOOKUP(Sales_fact[[#This Row],[Product_ID]],Product_Dim!A:A,Product_Dim!C:C,"OTHERS") -> Beauty
A70: SALE68 | B70: 45270 | C70: CUST1372 | D70: PROD72 | E70: =TRIM(Sales_fact[[#This Row],[Store_ID]]) -> STORE10 | F70: 4 | G70: =IF(ISBLANK(F70),MODE($F$2:$F$2001),F70) -> 4 | H70: 62.48 | I70: =IF(ISBLANK(H70),AVERAGE($H$2:$H$2001),H70) -> 62.48 | J70: 0.18 | K70: =IF(ISBLANK(J70),MODE($J$2:$J$2001),J70) -> 0.18 | L70: Credit Card | M70: 204.9344 | N70: =G70*I70*(1-K70) -> 204.9344 | O70: =_xlfn.XLOOKUP(Sales_fact[[#This Row],[Customer_ID]],'Customer_Dim'!A:A,'Customer_Dim'!K:K,"Not Found") -> Bronze | P70: =_xlfn.XLOOKUP(Sales_fact[[#This Row],[Customer_ID]],'Customer_Dim'!A:A, 'Customer_Dim'!E:E, "Not Found") -> 28 | Q70: =VLOOKUP(Sales_fact[[#This Row],[Customer_ID]], 'Customer_Dim'!A:F, 6, FALSE) -> Male | R70: =_xlfn.XLOOKUP(Sales_fact[[#This Row],[Product_ID]],Product_Dim!A:A,Product_Dim!C:C,"OTHERS") -> Sports
A71: SALE69 | B71: 45897 | C71: CUST1423 | D71: PROD13 | E71: =TRIM(Sales_fact[[#This Row],[Store_ID]]) -> STORE16 | F71: 4 | G71: =IF(ISBLANK(F71),MODE($F$2:$F$2001),F71) -> 4 | H71: 561.24 | I71: =IF(ISBLANK(H71),AVERAGE($H$2:$H$2001),H71) -> 561.24 | J71: 0.24 | K71: =IF(ISBLANK(J71),MODE($J$2:$J$2001),J71) -> 0.24 | L71: Credit Card | M71: 1706.1696 | N71: =G71*I71*(1-K71) -> 1706.1696 | O71: =_xlfn.XLOOKUP(Sales_fact[[#This Row],[Customer_ID]],'Customer_Dim'!A:A,'Customer_Dim'!K:K,"Not Found") -> Silver | P71: =_xlfn.XLOOKUP(Sales_fact[[#This Row],[Customer_ID]],'Customer_Dim'!A:A, 'Customer_Dim'!E:E, "Not Found") -> 35 | Q71: =VLOOKUP(Sales_fact[[#This Row],[Customer_ID]], 'Customer_Dim'!A:F, 6, FALSE) -> Male | R71: =_xlfn.XLOOKUP(Sales_fact[[#This Row],[Product_ID]],Product_Dim!A:A,Product_Dim!C:C,"OTHERS") -> Electronics
A72: SALE70 | B72: 45849 | C72: CUST1058 | D72: PROD60 | E72: =TRIM(Sales_fact[[#This Row],[Store_ID]]) -> STORE5 | F72: 3 | G72: =IF(ISBLANK(F72),MODE($F$2:$F$2001),F72) -> 3 | H72: 92.24 | I72: =IF(ISBLANK(H72),AVERAGE($H$2:$H$2001),H72) -> 92.24 | J72: 0.28 | K72: =IF(ISBLANK(J72),MODE($J$2:$J$2001),J72) -> 0.28 | L72: COD | N72: =G72*I72*(1-K72) -> 199.2384 | O72: =_xlfn.XLOOKUP(Sales_fact[[#This Row],[Customer_ID]],'Customer_Dim'!A:A,'Customer_Dim'!K:K,"Not Found") -> Platinum | P72: =_xlfn.XLOOKUP(Sales_fact[[#This Row],[Customer_ID]],'Customer_Dim'!A:A, 'Customer_Dim'!E:E, "Not Found") -> 51 | Q72: =VLOOKUP(Sales_fact[[#This Row],[Customer_ID]], 'Customer_Dim'!A:F, 6, FALSE) -> Male | R72: =_xlfn.XLOOKUP(Sales_fact[[#This Row],[Product_ID]],Product_Dim!A:A,Product_Dim!C:C,"OTHERS") -> Beauty
A73: SALE71 | B73: 45889 | C73: CUST1168 | D73: PROD72 | E73: =TRIM(Sales_fact[[#This Row],[Store_ID]]) -> STORE1 | F73: 2 | G73: =IF(ISBLANK(F73),MODE($F$2:$F$2001),F73) -> 2 | H73: 668.3 | I73: =IF(ISBLANK(H73),AVERAGE($H$2:$H$2001),H73) -> 668.3 | J73: 0.07 | K73: =IF(ISBLANK(J73),MODE($J$2:$J$2001),J73) -> 0.07 | L73: Credit Card | M73: 1243.038 | N73: =G73*I73*(1-K73) -> 1243.038 | O73: =_xlfn.XLOOKUP(Sales_fact[[#This Row],[Customer_ID]],'Customer_Dim'!A:A,'Customer_Dim'!K:K,"Not Found") -> Platinum | P73: =_xlfn.XLOOKUP(Sales_fact[[#This Row],[Customer_ID]],'Customer_Dim'!A:A, 'Customer_Dim'!E:E, "Not Found") -> 36 | Q73: =VLOOKUP(Sales_fact[[#This Row],[Customer_ID]], 'Customer_Dim'!A:F, 6, FALSE) -> Female | R73: =_xlfn.XLOOKUP(Sales_fact[[#This Row],[Product_ID]],Product_Dim!A:A,Product_Dim!C:C,"OTHERS") -> Sports
A74: SALE72 | B74: 45533 | C74: CUST1409 | D74: PROD38 | E74: =TRIM(Sales_fact[[#This Row],[Store_ID]]) -> STORE5 | F74: 1 | G74: =IF(ISBLANK(F74),MODE($F$2:$F$2001),F74) -> 1 | H74: 553.82 | I74: =IF(ISBLANK(H74),AVERAGE($H$2:$H$2001),H74) -> 553.82 | J74: 0.09 | K74: =IF(ISBLANK(J74),MODE($J$2:$J$2001),J74) -> 0.09 | L74: Credit Card | M74: 503.9762 | N74: =G74*I74*(1-K74) -> 503.9762 | O74: =_xlfn.XLOOKUP(Sales_fact[[#This Row],[Customer_ID]],'Customer_Dim'!A:A,'Customer_Dim'!K:K,"Not Found") -> Gold | P74: =_xlfn.XLOOKUP(Sales_fact[[#This Row],[Customer_ID]],'Customer_Dim'!A:A, 'Customer_Dim'!E:E, "Not Found") -> 55 | Q74: =VLOOKUP(Sales_fact[[#This Row],[Customer_ID]], 'Customer_Dim'!A:F, 6, FALSE) -> Male | R74: =_xlfn.XLOOKUP(Sales_fact[[#This Row],[Product_ID]],Product_Dim!A:A,Product_Dim!C:C,"OTHERS") -> Sports
A75: SALE73 | B75: 45626 | C75: CUST1037 | D75: PROD45 | E75: =TRIM(Sales_fact[[#This Row],[Store_ID]]) -> STORE11 | F75: 2 | G75: =IF(ISBLANK(F75),MODE($F$2:$F$2001),F75) -> 2 | H75: 556.43 | I75: =IF(ISBLANK(H75),AVERAGE($H$2:$H$2001),H75) -> 556.43 | J75: 0.13 | K75: =IF(ISBLANK(J75),MODE($J$2:$J$2001),J75) -> 0.13 | L75: Credit Card | M75: 968.1882 | N75: =G75*I75*(1-K75) -> 968.1882 | O75: =_xlfn.XLOOKUP(Sales_fact[[#This Row],[Customer_ID]],'Customer_Dim'!A:A,'Customer_Dim'!K:K,"Not Found") -> UNKNOWN | P75: =_xlfn.XLOOKUP(Sales_fact[[#This Row],[Customer_ID]],'Customer_Dim'!A:A, 'Customer_Dim'!E:E, "Not Found") -> 27 | Q75: =VLOOKUP(Sales_fact[[#This Row],[Customer_ID]], 'Customer_Dim'!A:F, 6, FALSE) -> Female | R75: =_xlfn.XLOOKUP(Sales_fact[[#This Row],[Product_ID]],Product_Dim!A:A,Product_Dim!C:C,"OTHERS") -> Sports
A76: SALE74 | B76: 45942 | C76: CUST1273 | D76: PROD20 | E76: =TRIM(Sales_fact[[#This Row],[Store_ID]]) -> STORE8 | F76: 1 | G76: =IF(ISBLANK(F76),MODE($F$2:$F$2001),F76) -> 1 | H76: 184.98 | I76: =IF(ISBLANK(H76),AVERAGE($H$2:$H$2001),H76) -> 184.98 | J76: 0.1 | K76: =IF(ISBLANK(J76),MODE($J$2:$J$2001),J76) -> 0.1 | L76: COD | M76: 166.482 | N76: =G76*I76*(1-K76) -> 166.482 | O76: =_xlfn.XLOOKUP(Sales_fact[[#This Row],[Customer_ID]],'Customer_Dim'!A:A,'Customer_Dim'!K:K,"Not Found") -> Bronze | P76: =_xlfn.XLOOKUP(Sales_fact[[#This Row],[Customer_ID]],'Customer_Dim'!A:A, 'Customer_Dim'!E:E, "Not Found") -> 23 | Q76: =VLOOKUP(Sales_fact[[#This Row],[Customer_ID]], 'Customer_Dim'!A:F, 6, FALSE) -> Male | R76: =_xlfn.XLOOKUP(Sales_fact[[#This Row],[Product_ID]],Product_Dim!A:A,Product_Dim!C:C,"OTHERS") -> Sports
A77: SALE75 | B77: 45500 | C77: CUST1035 | D77: PROD97 | E77: =TRIM(Sales_fact[[#This Row],[Store_ID]]) -> STORE12 | F77: 4 | G77: =IF(ISBLANK(F77),MODE($F$2:$F$2001),F77) -> 4 | H77: 700.18 | I77: =IF(ISBLANK(H77),AVERAGE($H$2:$H$2001),H77) -> 700.18 | J77: 0.23 | K77: =IF(ISBLANK(J77),MODE($J$2:$J$2001),J77) -> 0.23 | L77: Credit Card | M77: 2156.5544 | N77: =G77*I77*(1-K77) -> 2156.5544 | O77: =_xlfn.XLOOKUP(Sales_fact[[#This Row],[Customer_ID]],'Customer_Dim'!A:A,'Customer_Dim'!K:K,"Not Found") -> Silver | P77: =_xlfn.XLOOKUP(Sales_fact[[#This Row],[Customer_ID]],'Customer_Dim'!A:A, 'Customer_Dim'!E:E, "Not Found") -> 52 | Q77: =VLOOKUP(Sales_fact[[#This Row],[Customer_ID]], 'Customer_Dim'!A:F, 6, FALSE) -> Male | R77: =_xlfn.XLOOKUP(Sales_fact[[#This Row],[Product_ID]],Product_Dim!A:A,Product_Dim!C:C,"OTHERS") -> Sports
A78: SALE76 | B78: 45285 | C78: CUST1019 | D78: PROD76 | E78: =TRIM(Sales_fact[[#This Row],[Store_ID]]) -> STORE10 | F78: 2 | G78: =IF(ISBLANK(F78),MODE($F$2:$F$2001),F78) -> 2 | H78: 686.31 | I78: =IF(ISBLANK(H78),AVERAGE($H$2:$H$2001),H78) -> 686.31 | J78: 0.25 | K78: =IF(ISBLANK(J78),MODE($J$2:$J$2001),J78) -> 0.25 | L78: Credit Card | M78: 1029.465 | N78: =G78*I78*(1-K78) -> 1029.465 | O78: =_xlfn.XLOOKUP(Sales_fact[[#This Row],[Customer_ID]],'Customer_Dim'!A:A,'Customer_Dim'!K:K,"Not Found") -> Platinum | P78: =_xlfn.XLOOKUP(Sales_fact[[#This Row],[Customer_ID]],'Customer_Dim'!A:A, 'Customer_Dim'!E:E, "Not Found") -> 46 | Q78: =VLOOKUP(Sales_fact[[#This Row],[Customer_ID]], 'Customer_Dim'!A:F, 6, FALSE) -> Female | R78: =_xlfn.XLOOKUP(Sales_fact[[#This Row],[Product_ID]],Product_Dim!A:A,Product_Dim!C:C,"OTHERS") -> Electronics
A79: SALE77 | B79: 45800 | C79: CUST1007 | D79: PROD67 | E79: =TRIM(Sales_fact[[#This Row],[Store_ID]]) -> STORE15 | F79: 1 | G79: =IF(ISBLANK(F79),MODE($F$2:$F$2001),F79) -> 1 | H79: 687.82 | I79: =IF(ISBLANK(H79),AVERAGE($H$2:$H$2001),H79) -> 687.82 | J79: 0.27 | K79: =IF(ISBLANK(J79),MODE($J$2:$J$2001),J79) -> 0.27 | L79: COD | M79: 502.1086 | N79: =G79*I79*(1-K79) -> 502.1086 | O79: =_xlfn.XLOOKUP(Sales_fact[[#This Row],[Customer_ID]],'Customer_Dim'!A:A,'Customer_Dim'!K:K,"Not Found") -> Bronze | P79: =_xlfn.XLOOKUP(Sales_fact[[#This Row],[Customer_ID]],'Customer_Dim'!A:A, 'Customer_Dim'!E:E, "Not Found") -> 29 | Q79: =VLOOKUP(Sales_fact[[#This Row],[Customer_ID]], 'Customer_Dim'!A:F, 6, FALSE) -> Female | R79: =_xlfn.XLOOKUP(Sales_fact[[#This Row],[Product_ID]],Product_Dim!A:A,Product_Dim!C:C,"OTHERS") -> Electronics
A80: SALE78 | B80: 45609 | C80: CUST1221 | D80: PROD83 | E80: =TRIM(Sales_fact[[#This Row],[Store_ID]]) -> STORE8 | F80: 2 | G80: =IF(ISBLANK(F80),MODE($F$2:$F$2001),F80) -> 2 | H80: 900.55 | I80: =IF(ISBLANK(H80),AVERAGE($H$2:$H$2001),H80) -> 900.55 | J80: 0.16 | K80: =IF(ISBLANK(J80),MODE($J$2:$J$2001),J80) -> 0.16 | L80: Credit Card | M80: 1512.924 | N80: =G80*I80*(1-K80) -> 1512.924 | O80: =_xlfn.XLOOKUP(Sales_fact[[#This Row],[Customer_ID]],'Customer_Dim'!A:A,'Customer_Dim'!K:K,"Not Found") -> Platinum | P80: =_xlfn.XLOOKUP(Sales_fact[[#This Row],[Customer_ID]],'Customer_Dim'!A:A, 'Customer_Dim'!E:E, "Not Found") -> 38 | Q80: =VLOOKUP(Sales_fact[[#This Row],[Customer_ID]], 'Customer_Dim'!A:F, 6, FALSE) -> Male | R80: =_xlfn.XLOOKUP(Sales_fact[[#This Row],[Product_ID]],Product_Dim!A:A,Product_Dim!C:C,"OTHERS") -> Beauty
A81: SALE79 | B81: 45268 | C81: CUST1115 | D81: PROD21 | E81: =TRIM(Sales_fact[[#This Row],[Store_ID]]) -> STORE2 | F81: 1 | G81: =IF(ISBLANK(F81),MODE($F$2:$F$2001),F81) -> 1 | H81: 341.17 | I81: =IF(ISBLANK(H81),AVERAGE($H$2:$H$2001),H81) -> 341.17 | J81: 0.15 | K81: =IF(ISBLANK(J81),MODE($J$2:$J$2001),J81) -> 0.15 | L81: Credit Card | M81: 289.9945 | N81: =G81*I81*(1-K81) -> 289.9945 | O81: =_xlfn.XLOOKUP(Sales_fact[[#This Row],[Customer_ID]],'Customer_Dim'!A:A,'Customer_Dim'!K:K,"Not Found") -> Platinum | P81: =_xlfn.XLOOKUP(Sales_fact[[#This Row],[Customer_ID]],'Customer_Dim'!A:A, 'Customer_Dim'!E:E, "Not Found") -> 53 | Q81: =VLOOKUP(Sales_fact[[#This Row],[Customer_ID]], 'Customer_Dim'!A:F, 6, FALSE) -> Female | R81: =_xlfn.XLOOKUP(Sales_fact[[#This Row],[Product_ID]],Product_Dim!A:A,Product_Dim!C:C,"OTHERS") -> Home
A82: SALE80 | B82: 45885 | C82: CUST1176 | D82: PROD52 | E82: =TRIM(Sales_fact[[#This Row],[Store_ID]]) -> STORE8 | F82: 1 | G82: =IF(ISBLANK(F82),MODE($F$2:$F$2001),F82) -> 1 | H82: 442.27 | I82: =IF(ISBLANK(H82),AVERAGE($H$2:$H$2001),H82) -> 442.27 | J82: 0.06 | K82: =IF(ISBLANK(J82),MODE($J$2:$J$2001),J82) -> 0.06 | L82: COD | M82: 415.7338 | N82: =G82*I82*(1-K82) -> 415.7338 | O82: =_xlfn.XLOOKUP(Sales_fact[[#This Row],[Customer_ID]],'Customer_Dim'!A:A,'Customer_Dim'!K:K,"Not Found") -> Silver | P82: =_xlfn.XLOOKUP(Sales_fact[[#This Row],[Customer_ID]],'Customer_Dim'!A:A, 'Customer_Dim'!E:E, "Not Found") -> 48 | Q82: =VLOOKUP(Sales_fact[[#This Row],[Customer_ID]], 'Customer_Dim'!A:F, 6, FALSE) -> Male | R82: =_xlfn.XLOOKUP(Sales_fact[[#This Row],[Product_ID]],Product_Dim!A:A,Product_Dim!C:C,"OTHERS") -> Sports
A83: SALE81 | B83: 45616 | C83: CUST1253 | D83: PROD71 | E83: =TRIM(Sales_fact[[#This Row],[Store_ID]]) -> STORE9 | F83: 1 | G83: =IF(ISBLANK(F83),MODE($F$2:$F$2001),F83) -> 1 | H83: 363.73 | I83: =IF(ISBLANK(H83),AVERAGE($H$2:$H$2001),H83) -> 363.73 | J83: 0.25 | K83: =IF(ISBLANK(J83),MODE($J$2:$J$2001),J83) -> 0.25 | L83: PayPal | M83: 272.7975 | N83: =G83*I83*(1-K83) -> 272.7975 | O83: =_xlfn.XLOOKUP(Sales_fact[[#This Row],[Customer_ID]],'Customer_Dim'!A:A,'Customer_Dim'!K:K,"Not Found") -> Bronze | P83: =_xlfn.XLOOKUP(Sales_fact[[#This Row],[Customer_ID]],'Customer_Dim'!A:A, 'Customer_Dim'!E:E, "Not Found") -> 32 | Q83: =VLOOKUP(Sales_fact[[#This Row],[Customer_ID]], 'Customer_Dim'!A:F, 6, FALSE) -> Male | R83: =_xlfn.XLOOKUP(Sales_fact[[#This Row],[Product_ID]],Product_Dim!A:A,Product_Dim!C:C,"OTHERS") -> Beauty
A84: SALE82 | B84: 45518 | C84: CUST1378 | D84: PROD91 | E84: =TRIM(Sales_fact[[#This Row],[Store_ID]]) -> STORE17 | F84: 2 | G84: =IF(ISBLANK(F84),MODE($F$2:$F$2001),F84) -> 2 | H84: 601.33 | I84: =IF(ISBLANK(H84),AVERAGE($H$2:$H$2001),H84) -> 601.33 | J84: 0.16 | K84: =IF(ISBLANK(J84),MODE($J$2:$J$2001),J84) -> 0.16 | L84: PayPal | M84: 1010.2344 | N84: =G84*I84*(1-K84) -> 1010.2344 | O84: =_xlfn.XLOOKUP(Sales_fact[[#This Row],[Customer_ID]],'Customer_Dim'!A:A,'Customer_Dim'!K:K,"Not Found") -> Bronze | P84: =_xlfn.XLOOKUP(Sales_fact[[#This Row],[Customer_ID]],'Customer_Dim'!A:A, 'Customer_Dim'!E:E, "Not Found") -> 44 | Q84: =VLOOKUP(Sales_fact[[#This Row],[Customer_ID]], 'Customer_Dim'!A:F, 6, FALSE) -> Female | R84: =_xlfn.XLOOKUP(Sales_fact[[#This Row],[Product_ID]],Product_Dim!A:A,Product_Dim!C:C,"OTHERS") -> Clothing
A85: SALE83 | B85: 45427 | C85: CUST1403 | D85: PROD17 | E85: =TRIM(Sales_fact[[#This Row],[Store_ID]]) -> STORE18 | F85: 4 | G85: =IF(ISBLANK(F85),MODE($F$2:$F$2001),F85) -> 4 | H85: 34.39 | I85: =IF(ISBLANK(H85),AVERAGE($H$2:$H$2001),H85) -> 34.39 | J85: 0.03 | K85: =IF(ISBLANK(J85),MODE($J$2:$J$2001),J85) -> 0.03 | L85: PayPal | M85: 133.4332 | N85: =G85*I85*(1-K85) -> 133.4332 | O85: =_xlfn.XLOOKUP(Sales_fact[[#This Row],[Customer_ID]],'Customer_Dim'!A:A,'Customer_Dim'!K:K,"Not Found") -> Bronze | P85: =_xlfn.XLOOKUP(Sales_fact[[#This Row],[Customer_ID]],'Customer_Dim'!A:A, 'Customer_Dim'!E:E, "Not Found") -> 34 | Q85: =VLOOKUP(Sales_fact[[#This Row],[Customer_ID]], 'Customer_Dim'!A:F, 6, FALSE) -> Male | R85: =_xlfn.XLOOKUP(Sales_fact[[#This Row],[Product_ID]],Product_Dim!A:A,Product_Dim!C:C,"OTHERS") -> Sports
A86: SALE84 | B86: 45268 | C86: CUST1423 | D86: PROD46 | E86: =TRIM(Sales_fact[[#This Row],[Store_ID]]) -> STORE17 | F86: 1 | G86: =IF(ISBLANK(F86),MODE($F$2:$F$2001),F86) -> 1 | H86: 773.57 | I86: =IF(ISBLANK(H86),AVERAGE($H$2:$H$2001),H86) -> 773.57 | J86: 0.05 | K86: =IF(ISBLANK(J86),MODE($J$2:$J$2001),J86) -> 0.05 | L86: COD | N86: =G86*I86*(1-K86) -> 734.8915 | O86: =_xlfn.XLOOKUP(Sales_fact[[#This Row],[Customer_ID]],'Customer_Dim'!A:A,'Customer_Dim'!K:K,"Not Found") -> Silver | P86: =_xlfn.XLOOKUP(Sales_fact[[#This Row],[Customer_ID]],'Customer_Dim'!A:A, 'Customer_Dim'!E:E, "Not Found") -> 35 | Q86: =VLOOKUP(Sales_fact[[#This Row],[Customer_ID]], 'Customer_Dim'!A:F, 6, FALSE) -> Male | R86: =_xlfn.XLOOKUP(Sales_fact[[#This Row],[Product_ID]],Product_Dim!A:A,Product_Dim!C:C,"OTHERS") -> Clothing
A87: SALE85 | B87: 45282 | C87: CUST1054 | D87: PROD88 | E87: =TRIM(Sales_fact[[#This Row],[Store_ID]]) -> STORE7 | F87: 4 | G87: =IF(ISBLANK(F87),MODE($F$2:$F$2001),F87) -> 4 | H87: 127.1 | I87: =IF(ISBLANK(H87),AVERAGE($H$2:$H$2001),H87) -> 127.1 | J87: 0.24 | K87: =IF(ISBLANK(J87),MODE($J$2:$J$2001),J87) -> 0.24 | L87: COD | M87: 386.384 | N87: =G87*I87*(1-K87) -> 386.384 | O87: =_xlfn.XLOOKUP(Sales_fact[[#This Row],[Customer_ID]],'Customer_Dim'!A:A,'Customer_Dim'!K:K,"Not Found") -> Platinum | P87: =_xlfn.XLOOKUP(Sales_fact[[#This Row],[Customer_ID]],'Customer_Dim'!A:A, 'Customer_Dim'!E:E, "Not Found") -> 24 | Q87: =VLOOKUP(Sales_fact[[#This Row],[Customer_ID]], 'Customer_Dim'!A:F, 6, FALSE) -> Male | R87: =_xlfn.XLOOKUP(Sales_fact[[#This Row],[Product_ID]],Product_Dim!A:A,Product_Dim!C:C,"OTHERS") -> Sports
A88: SALE86 | B88: 45545 | C88: CUST1303 | D88: PROD20 | E88: =TRIM(Sales_fact[[#This Row],[Store_ID]]) -> STORE3 | F88: 3 | G88: =IF(ISBLANK(F88),MODE($F$2:$F$2001),F88) -> 3 | H88: 899.58 | I88: =IF(ISBLANK(H88),AVERAGE($H$2:$H$2001),H88) -> 899.58 | J88: 0.28 | K88: =IF(ISBLANK(J88),MODE($J$2:$J$2001),J88) -> 0.28 | L88: PayPal | M88: 1943.0928 | N88: =G88*I88*(1-K88) -> 1943.0928 | O88: =_xlfn.XLOOKUP(Sales_fact[[#This Row],[Customer_ID]],'Customer_Dim'!A:A,'Customer_Dim'!K:K,"Not Found") -> Platinum | P88: =_xlfn.XLOOKUP(Sales_fact[[#This Row],[Customer_ID]],'Customer_Dim'!A:A, 'Customer_Dim'!E:E, "Not Found") -> 23 | Q88: =VLOOKUP(Sales_fact[[#This Row],[Customer_ID]], 'Customer_Dim'!A:F, 6, FALSE) -> Female | R88: =_xlfn.XLOOKUP(Sales_fact[[#This Row],[Product_ID]],Product_Dim!A:A,Product_Dim!C:C,"OTHERS") -> Sports
A89: SALE87 | B89: 45755 | C89: CUST1327 | D89: PROD1 | E89: =TRIM(Sales_fact[[#This Row],[Store_ID]]) -> STORE10 | F89: 3 | G89: =IF(ISBLANK(F89),MODE($F$2:$F$2001),F89) -> 3 | H89: 964.39 | I89: =IF(ISBLANK(H89),AVERAGE($H$2:$H$2001),H89) -> 964.39 | J89: 0.04 | K89: =IF(ISBLANK(J89),MODE($J$2:$J$2001),J89) -> 0.04 | L89: Credit Card | M89: 2777.4432 | N89: =G89*I89*(1-K89) -> 2777.4432 | O89: =_xlfn.XLOOKUP(Sales_fact[[#This Row],[Customer_ID]],'Customer_Dim'!A:A,'Customer_Dim'!K:K,"Not Found") -> Bronze | P89: =_xlfn.XLOOKUP(Sales_fact[[#This Row],[Customer_ID]],'Customer_Dim'!A:A, 'Customer_Dim'!E:E, "Not Found") -> 62 | Q89: =VLOOKUP(Sales_fact[[#This Row],[Customer_ID]], 'Customer_Dim'!A:F, 6, FALSE) -> Female | R89: =_xlfn.XLOOKUP(Sales_fact[[#This Row],[Product_ID]],Product_Dim!A:A,Product_Dim!C:C,"OTHERS") -> Clothing
A90: SALE88 | B90: 45588 | C90: CUST1183 | D90: PROD38 | E90: =TRIM(Sales_fact[[#This Row],[Store_ID]]) -> STORE0 | F90: 2 | G90: =IF(ISBLANK(F90),MODE($F$2:$F$2001),F90) -> 2 | H90: 217.83 | I90: =IF(ISBLANK(H90),AVERAGE($H$2:$H$2001),H90) -> 217.83 | J90: 0.14 | K90: =IF(ISBLANK(J90),MODE($J$2:$J$2001),J90) -> 0.14 | L90: PayPal | M90: 374.6676 | N90: =G90*I90*(1-K90) -> 374.6676 | O90: =_xlfn.XLOOKUP(Sales_fact[[#This Row],[Customer_ID]],'Customer_Dim'!A:A,'Customer_Dim'!K:K,"Not Found") -> Platinum | P90: =_xlfn.XLOOKUP(Sales_fact[[#This Row],[Customer_ID]],'Customer_Dim'!A:A, 'Customer_Dim'!E:E, "Not Found") -> 18 | Q90: =VLOOKUP(Sales_fact[[#This Row],[Customer_ID]], 'Customer_Dim'!A:F, 6, FALSE) -> Male | R90: =_xlfn.XLOOKUP(Sales_fact[[#This Row],[Product_ID]],Product_Dim!A:A,Product_Dim!C:C,"OTHERS") -> Sports
A91: SALE89 | B91: 45848 | C91: CUST1143 | D91: PROD17 | E91: =TRIM(Sales_fact[[#This Row],[Store_ID]]) -> STORE1 | F91: 4 | G91: =IF(ISBLANK(F91),MODE($F$2:$F$2001),F91) -> 4 | H91: 187.71 | I91: =IF(ISBLANK(H91),AVERAGE($H$2:$H$2001),H91) -> 187.71 | J91: 0.06 | K91: =IF(ISBLANK(J91),MODE($J$2:$J$2001),J91) -> 0.06 | L91: COD | M91: 705.7896 | N91: =G91*I91*(1-K91) -> 705.7896 | O91: =_xlfn.XLOOKUP(Sales_fact[[#This Row],[Customer_ID]],'Customer_Dim'!A:A,'Customer_Dim'!K:K,"Not Found") -> Bronze | P91: =_xlfn.XLOOKUP(Sales_fact[[#This Row],[Customer_ID]],'Customer_Dim'!A:A, 'Customer_Dim'!E:E, "Not Found") -> 46 | Q91: =VLOOKUP(Sales_fact[[#This Row],[Customer_ID]], 'Customer_Dim'!A:F, 6, FALSE) -> Male | R91: =_xlfn.XLOOKUP(Sales_fact[[#This Row],[Product_ID]],Product_Dim!A:A,Product_Dim!C:C,"OTHERS") -> Sports
A92: SALE90 | B92: 45577 | C92: CUST1010 | D92: PROD33 | E92: =TRIM(Sales_fact[[#This Row],[Store_ID]]) -> STORE18 | F92: 2 | G92: =IF(ISBLANK(F92),MODE($F$2:$F$2001),F92) -> 2 | H92: 350.12 | I92: =IF(ISBLANK(H92),AVERAGE($H$2:$H$2001),H92) -> 350.12 | J92: 0.12 | K92: =IF(ISBLANK(J92),MODE($J$2:$J$2001),J92) -> 0.12 | L92: COD | M92: 616.2112 | N92: =G92*I92*(1-K92) -> 616.2112 | O92: =_xlfn.XLOOKUP(Sales_fact[[#This Row],[Customer_ID]],'Customer_Dim'!A:A,'Customer_Dim'!K:K,"Not Found") -> Bronze | P92: =_xlfn.XLOOKUP(Sales_fact[[#This Row],[Customer_ID]],'Customer_Dim'!A:A, 'Customer_Dim'!E:E, "Not Found") -> 53 | Q92: =VLOOKUP(Sales_fact[[#This Row],[Customer_ID]], 'Customer_Dim'!A:F, 6, FALSE) -> Male | R92: =_xlfn.XLOOKUP(Sales_fact[[#This Row],[Product_ID]],Product_Dim!A:A,Product_Dim!C:C,"OTHERS") -> Home
A93: SALE91 | B93: 45312 | C93: CUST1406 | D93: PROD16 | E93: =TRIM(Sales_fact[[#This Row],[Store_ID]]) -> STORE1 | F93: 4 | G93: =IF(ISBLANK(F93),MODE($F$2:$F$2001),F93) -> 4 | H93: 102.19 | I93: =IF(ISBLANK(H93),AVERAGE($H$2:$H$2001),H93) -> 102.19 | J93: 0.17 | K93: =IF(ISBLANK(J93),MODE($J$2:$J$2001),J93) -> 0.17 | L93: PayPal | M93: 339.2708 | N93: =G93*I93*(1-K93) -> 339.2708 | O93: =_xlfn.XLOOKUP(Sales_fact[[#This Row],[Customer_ID]],'Customer_Dim'!A:A,'Customer_Dim'!K:K,"Not Found") -> Gold | P93: =_xlfn.XLOOKUP(Sales_fact[[#This Row],[Customer_ID]],'Customer_Dim'!A:A, 'Customer_Dim'!E:E, "Not Found") -> 23 | Q93: =VLOOKUP(Sales_fact[[#This Row],[Customer_ID]], 'Customer_Dim'!A:F, 6, FALSE) -> Female | R93: =_xlfn.XLOOKUP(Sales_fact[[#This Row],[Product_ID]],Product_Dim!A:A,Product_Dim!C:C,"OTHERS") -> OTHERS
A94: SALE92 | B94: 45350 | C94: CUST1007 | D94: PROD86 | E94: =TRIM(Sales_fact[[#This Row],[Store_ID]]) -> STORE4 | F94: 1 | G94: =IF(ISBLANK(F94),MODE($F$2:$F$2001),F94) -> 1 | H94: 696.53 | I94: =IF(ISBLANK(H94),AVERAGE($H$2:$H$2001),H94) -> 696.53 | J94: 0.17 | K94: =IF(ISBLANK(J94),MODE($J$2:$J$2001),J94) -> 0.17 | L94: Credit Card | M94: 578.1199 | N94: =G94*I94*(1-K94) -> 578.1199 | O94: =_xlfn.XLOOKUP(Sales_fact[[#This Row],[Customer_ID]],'Customer_Dim'!A:A,'Customer_Dim'!K:K,"Not Found") -> Bronze | P94: =_xlfn.XLOOKUP(Sales_fact[[#This Row],[Customer_ID]],'Customer_Dim'!A:A, 'Customer_Dim'!E:E, "Not Found") -> 29 | Q94: =VLOOKUP(Sales_fact[[#This Row],[Customer_ID]], 'Customer_Dim'!A:F, 6, FALSE) -> Female | R94: =_xlfn.XLOOKUP(Sales_fact[[#This Row],[Product_ID]],Product_Dim!A:A,Product_Dim!C:C,"OTHERS") -> Home
A95: SALE93 | B95: 45657 | C95: CUST1065 | D95: PROD19 | E95: =TRIM(Sales_fact[[#This Row],[Store_ID]]) -> STORE4 | F95: 2 | G95: =IF(ISBLANK(F95),MODE($F$2:$F$2001),F95) -> 2 | H95: 327.52 | I95: =IF(ISBLANK(H95),AVERAGE($H$2:$H$2001),H95) -> 327.52 | J95: 0.15 | K95: =IF(ISBLANK(J95),MODE($J$2:$J$2001),J95) -> 0.15 | L95: PayPal | M95: 556.784 | N95: =G95*I95*(1-K95) -> 556.784 | O95: =_xlfn.XLOOKUP(Sales_fact[[#This Row],[Customer_ID]],'Customer_Dim'!A:A,'Customer_Dim'!K:K,"Not Found") -> Silver | P95: =_xlfn.XLOOKUP(Sales_fact[[#This Row],[Customer_ID]],'Customer_Dim'!A:A, 'Customer_Dim'!E:E, "Not Found") -> 21 | Q95: =VLOOKUP(Sales_fact[[#This Row],[Customer_ID]], 'Customer_Dim'!A:F, 6, FALSE) -> Female | R95: =_xlfn.XLOOKUP(Sales_fact[[#This Row],[Product_ID]],Product_Dim!A:A,Product_Dim!C:C,"OTHERS") -> Sports
A96: SALE94 | B96: 45530 | C96: CUST1298 | D96: PROD97 | E96: =TRIM(Sales_fact[[#This Row],[Store_ID]]) -> STORE19 | F96: 2 | G96: =IF(ISBLANK(F96),MODE($F$2:$F$2001),F96) -> 2 | H96: 569.36 | I96: =IF(ISBLANK(H96),AVERAGE($H$2:$H$2001),H96) -> 569.36 | J96: 0.01 | K96: =IF(ISBLANK(J96),MODE($J$2:$J$2001),J96) -> 0.01 | L96: PayPal | N96: =G96*I96*(1-K96) -> 1127.3328 | O96: =_xlfn.XLOOKUP(Sales_fact[[#This Row],[Customer_ID]],'Customer_Dim'!A:A,'Customer_Dim'!K:K,"Not Found") -> Platinum | P96: =_xlfn.XLOOKUP(Sales_fact[[#This Row],[Customer_ID]],'Customer_Dim'!A:A, 'Customer_Dim'!E:E, "Not Found") -> 64 | Q96: =VLOOKUP(Sales_fact[[#This Row],[Customer_ID]], 'Customer_Dim'!A:F, 6, FALSE) -> Male | R96: =_xlfn.XLOOKUP(Sales_fact[[#This Row],[Product_ID]],Product_Dim!A:A,Product_Dim!C:C,"OTHERS") -> Sports
A97: SALE95 | B97: 45556 | C97: CUST1321 | D97: PROD99 | E97: =TRIM(Sales_fact[[#This Row],[Store_ID]]) -> STORE6 | F97: 2 | G97: =IF(ISBLANK(F97),MODE($F$2:$F$2001),F97) -> 2 | H97: 68.29 | I97: =IF(ISBLANK(H97),AVERAGE($H$2:$H$2001),H97) -> 68.29 | J97: 0.14 | K97: =IF(ISBLANK(J97),MODE($J$2:$J$2001),J97) -> 0.14 | L97: COD | M97: 117.4588 | N97: =G97*I97*(1-K97) -> 117.4588 | O97: =_xlfn.XLOOKUP(Sales_fact[[#This Row],[Customer_ID]],'Customer_Dim'!A:A,'Customer_Dim'!K:K,"Not Found") -> Bronze | P97: =_xlfn.XLOOKUP(Sales_fact[[#This Row],[Customer_ID]],'Customer_Dim'!A:A, 'Customer_Dim'!E:E, "Not Found") -> 21 | Q97: =VLOOKUP(Sales_fact[[#This Row],[Customer_ID]], 'Customer_Dim'!A:F, 6, FALSE) -> Female | R97: =_xlfn.XLOOKUP(Sales_fact[[#This Row],[Product_ID]],Product_Dim!A:A,Product_Dim!C:C,"OTHERS") -> Home
A98: SALE96 | B98: 45523 | C98: CUST1244 | D98: PROD50 | E98: =TRIM(Sales_fact[[#This Row],[Store_ID]]) -> STORE10 | F98: 1 | G98: =IF(ISBLANK(F98),MODE($F$2:$F$2001),F98) -> 1 | H98: 842.9 | I98: =IF(ISBLANK(H98),AVERAGE($H$2:$H$2001),H98) -> 842.9 | J98: 0.06 | K98: =IF(ISBLANK(J98),MODE($J$2:$J$2001),J98) -> 0.06 | L98: COD | M98: 792.326 | N98: =G98*I98*(1-K98) -> 792.326 | O98: =_xlfn.XLOOKUP(Sales_fact[[#This Row],[Customer_ID]],'Customer_Dim'!A:A,'Customer_Dim'!K:K,"Not Found") -> Bronze | P98: =_xlfn.XLOOKUP(Sales_fact[[#This Row],[Customer_ID]],'Customer_Dim'!A:A, 'Customer_Dim'!E:E, "Not Found") -> 19 | Q98: =VLOOKUP(Sales_fact[[#This Row],[Customer_ID]], 'Customer_Dim'!A:F, 6, FALSE) -> Male | R98: =_xlfn.XLOOKUP(Sales_fact[[#This Row],[Product_ID]],Product_Dim!A:A,Product_Dim!C:C,"OTHERS") -> Sports
A99: SALE97 | B99: 45587 | C99: CUST1287 | D99: PROD3 | E99: =TRIM(Sales_fact[[#This Row],[Store_ID]]) -> STORE3 | F99: 3 | G99: =IF(ISBLANK(F99),MODE($F$2:$F$2001),F99) -> 3 | H99: 751.94 | I99: =IF(ISBLANK(H99),AVERAGE($H$2:$H$2001),H99) -> 751.94 | J99: 0.26 | K99: =IF(ISBLANK(J99),MODE($J$2:$J$2001),J99) -> 0.26 | L99: PayPal | M99: 1669.3068 | N99: =G99*I99*(1-K99) -> 1669.3068 | O99: =_xlfn.XLOOKUP(Sales_fact[[#This Row],[Customer_ID]],'Customer_Dim'!A:A,'Customer_Dim'!K:K,"Not Found") -> Gold | P99: =_xlfn.XLOOKUP(Sales_fact[[#This Row],[Customer_ID]],'Customer_Dim'!A:A, 'Customer_Dim'!E:E, "Not Found") -> 22 | Q99: =VLOOKUP(Sales_fact[[#This Row],[Customer_ID]], 'Customer_Dim'!A:F, 6, FALSE) -> Female | R99: =_xlfn.XLOOKUP(Sales_fact[[#This Row],[Product_ID]],Product_Dim!A:A,Product_Dim!C:C,"OTHERS") -> OTHERS
A100: SALE98 | B100: 45580 | C100: CUST1131 | D100: PROD56 | E100: =TRIM(Sales_fact[[#This Row],[Store_ID]]) -> STORE7 | F100: 4 | G100: =IF(ISBLANK(F100),MODE($F$2:$F$2001),F100) -> 4 | H100: 476.28 | I100: =IF(ISBLANK(H100),AVERAGE($H$2:$H$2001),H100) -> 476.28 | J100: 0.17 | K100: =IF(ISBLANK(J100),MODE($J$2:$J$2001),J100) -> 0.17 | L100: Credit Card | M100: 1581.2496 | N100: =G100*I100*(1-K100) -> 1581.2496 | O100: =_xlfn.XLOOKUP(Sales_fact[[#This Row],[Customer_ID]],'Customer_Dim'!A:A,'Customer_Dim'!K:K,"Not Found") -> Bronze | P100: =_xlfn.XLOOKUP(Sales_fact[[#This Row],[Customer_ID]],'Customer_Dim'!A:A, 'Customer_Dim'!E:E, "Not Found") -> 34 | Q100: =VLOOKUP(Sales_fact[[#This Row],[Customer_ID]], 'Customer_Dim'!A:F, 6, FALSE) -> Female | R100: =_xlfn.XLOOKUP(Sales_fact[[#This Row],[Product_ID]],Product_Dim!A:A,Product_Dim!C:C,"OTHERS") -> Home
...

Sheet Sheet11
A1: Loyalty | B1: Sum of Total Amount
A2: Bronze | B2: 516065.73
A3: Gold | B3: 514204.38
A4: Not Found | B4: 26259.669
A5: Platinum | B5: 640304.87
A6: Silver | B6: 459016.44
A7: UNKNOWN | B7: 17512.335
A8: Grand Total | B8: 2173363.4

Sheet Pivot table
A2: Row Labels | B2: Sum of Total Amount | D2: Loyalty | E2: Sum of Total Amount
A3: STORE0 | B3: 85138.555 | D3: Bronze | E3: 516065.73
A4: STORE1 | B4: 100344.57 | D4: Gold | E4: 514204.38
A5: STORE10 | B5: 109791.72 | D5: Not Found | E5: 26259.669
A6: STORE11 | B6: 93048.141 | D6: Platinum | E6: 640304.87
A7: STORE12 | B7: 116829.22 | D7: Silver | E7: 459016.44
A8: STORE13 | B8: 114592.72 | D8: UNKNOWN | E8: 17512.335
A9: STORE14 | B9: 106248.28 | D9: Grand Total | E9: 2173363.4
A10: STORE15 | B10: 99679.086
A11: STORE16 | B11: 111704.94
A12: STORE17 | B12: 121555.11
A13: STORE18 | B13: 105447.24
A14: STORE19 | B14: 94225.723
A15: STORE2 | B15: 99010.55
A16: STORE3 | B16: 124243.99
A17: STORE4 | B17: 118814.12
A18: STORE5 | B18: 80926.716
A19: STORE6 | B19: 115435.49
A20: STORE7 | B20: 108127.36
A21: STORE8 | B21: 158933.98
... A23: Grand Total | B23: 2173363.4
A26: Row Labels | B26: Sum of Total Amount
A27: Female | B27: 1205587.4
A28: Male | B28: 941516.33
A29: #N/A | B29: 26259.669
A30: Grand Total | B30: 2173363.4
A33: Product category | B33: Sum of Total Amount
A34: Beauty | B34: 300905.69
A35: Clothing | B35: 354067.98
A36: Electronics | B36: 505496.07
A37: Home | B37: 424823.35
A38: OTHERS | B38: 46060.17
A39: Sports | B39: 542010.17
A40: Grand Total | B40: 2173363.4

Sheet Sheet12
A1: Product category | B1: Sum of Total Amount
A2: Beauty | B2: 300905.69
A3: Clothing | B3: 354067.98
A4: Electronics | B4: 505496.07
A5: Home | B5: 424823.35
A6: OTHERS | B6: 46060.17
A7: Sports | B7: 542010.17
A8: Grand Total | B8: 2173363.4

Sheet Charts

Sheet DASH BOARD
C1: SALES REPORT
